Workbook

Sheet Raw_Data
A1: Project_ID | B1: Client_ID | C1: Client_Name | D1: Project_Date | E1: Service | F1: Service_Category | G1: Industry | H1: Region | I1: Client_Type | J1: Project_Status | K1: Team_Size | L1: Project_Duration_Days | M1: Quoted_Value | N1: Discount | O1: Revenue | P1: Project_Cost | Q1: Profit | R1: Profit_Margin_Pct | S1: Lead_Source | T1: Marketing_Spend | U1: Customer_Rating | V1: Acquisition_Channel
A2: JSM10001 | B2: C0013 | C2: Client 0013 | D2: 2025-10-09 | E2: Social Media Marketing | F2: Social Media Marketing | G2: Education | H2: Ahmedabad | I2: Returning | J2: Completed | K2: 5 | L2: 46.0 | M2: 41100.0 | N2: 6200.0 | O2: 34900.0 | P2: 29300.0 | Q2: 5600.0 | R2: 16.05 | S2: Google | T2: 4300.0 | U2: 3.5 | V2: Organic Search
A3: JSM10002 | B3: C0112 | C3: Client 0112 | D3: 2025-08-27 | E3: SMM | F3: Social Media Marketing | G3: Manufacturing | H3: Pune | I3: Returning | J3: Completed | K3: 10 | L3: 35.0 | M3: 15000.0 | N3: 800.0 | O3: 14200.0 | P3: 7200.0 | Q3: 7000.0 | R3: 49.3 | S3: Direct | T3: 1000.0 | U3: 3.8 | V3: Direct
A4: JSM10003 | B4: C0415 | C4: Client 0415 | D4: 2025-01-07 | E4: content marketing | F4: Content Marketing | G4: Hospitality | H4: Bengaluru | I4: New | J4: Ongoing | K4: 4 | L4: 27.0 | M4: 33200.0 | N4: 3300.0 | O4: 29900.0 | P4: 16400.0 | Q4: 13500.0 | R4: 45.15 | S4: Referral | T4: 3800.0 | U4: 2.5 | V4: Social
A5: JSM10004 | B5: C0048 | C5: Client 0048 | D5: 2026-01-25 | E5: social media marketing | F5: Social Media Marketing | G5: Hospitality | H5: Mumbai | I5: Returning | J5: Completed | K5: 3 | L5: 48.0 | M5: 38600.0 | N5: 3900.0 | O5: 34700.0 | P5: 25800.0 | Q5: 8900.0 | R5: 25.65 | S5: Partner | T5: 3900.0 | U5: 4.0 | V5: Referral
A6: JSM10005 | B6: C0194 | C6: Client 0194 | D6: 2025-03-22 | E6: social media marketing | F6: Social Media Marketing | G6: Real Estate | H6: Delhi NCR | I6: New | J6: Completed | K6: 10 | L6: 28.0 | M6: 47100.0 | N6: 7100.0 | O6: 40000.0 | P6: 31200.0 | Q6: 8800.0 | R6: 22.0 | S6: Google | T6: 4100.0 | U6: 2.8 | V6: Paid Search
A7: JSM10006 | B7: C0041 | C7: Client 0041 | D7: 2025-08-27 | E7: content marketing | F7: Content Marketing | G7: Finance | H7: Bengaluru | I7: Returning | J7: Completed | K7: 3 | L7: 58.0 | M7: 68100.0 | N7: 3400.0 | O7: 64700.0 | P7: 45200.0 | Q7: 19500.0 | R7: 30.14 | S7: Social Media | T7: 10800.0 | U7: 3.4 | V7: Social
A8: JSM10007 | B8: C0344 | C8: Client 0344 | D8: 2025-10-01 | E8: Web Dev | F8: Web Development | G8: Real Estate | H8: Bengaluru | I8: New | J8: Completed | K8: 3 | L8: 52.0 | M8: 22700.0 | N8: 4500.0 | O8: 18200.0 | P8: 12400.0 | Q8: 5800.0 | R8: 31.87 | S8: Direct | T8: 1300.0 | U8: 3.8 | V8: Referral
A9: JSM10008 | B9: C0328 | C9: Client 0328 | D9: 2026-12-06 | E9: content marketing | F9: Content Marketing | G9: Healthcare | H9: Pune | I9: New | J9: Completed | K9: 10 | L9: 39.0 | M9: 40300.0 | N9: 4000.0 | O9: 36300.0 | P9: 23300.0 | Q9: 13000.0 | R9: 35.81 | S9: Google | T9: 4500.0 | U9: 4.9 | V9: Social
A10: JSM10009 | B10: C0138 | C10: Client 0138 | D10: 2025-03-09 | E10: online reputation management | F10: Online Reputation Management | G10: Finance | H10: Pune | I10: Returning | J10: Delayed | K10: 5 | L10: 19.0 | M10: 18600.0 | N10: 2800.0 | O10: 15800.0 | P10: 9800.0 | Q10: 6000.0 | R10: 37.97 | S10: Partner | T10: 1900.0 | U10: 4.2 | V10: Referral
A11: JSM10010 | B11: C0330 | C11: Client 0330 | D11: 2026-04-15 | E11: ORM | F11: Online Reputation Management | G11: Hospitality | H11: Ahmedabad | I11: New | J11: Completed | K11: 4 | L11: 45.0 | M11: 26300.0 | N11: 0.0 | O11: 26300.0 | P11: 12800.0 | Q11: 13500.0 | R11: 51.33 | S11: Email Campaign | T11: 4700.0 | U11: 3.4 | V11: Referral
A12: JSM10011 | B12: C0113 | C12: Client 0113 | D12: 2025-05-22 | E12: PPC | F12: PPC | G12: Education | H12: Bengaluru | I12: Returning | J12: Completed | K12: 10 | L12: 25.0 | M12: 62100.0 | N12: 3100.0 | O12: 59000.0 | P12: 26200.0 | Q12: 32800.0 | R12: 55.59 | S12: Partner | T12: 4000.0 | V12: Paid Search
A13: JSM10012 | B13: C0306 | C13: Client 0306 | D13: 2025-03-07 | E13: Online Reputation Management | F13: Online Reputation Management | G13: Hospitality | H13: Mumbai | I13: New | J13: Completed | K13: 8 | L13: 50.0 | M13: 65100.0 | N13: 6500.0 | O13: 58600.0 | P13: 44300.0 | Q13: 14300.0 | R13: 24.4 | S13: Partner | T13: 9400.0 | U13: 4.2 | V13: Organic Search
A14: JSM10013 | B14: C0394 | C14: Client 0394 | D14: 2026-10-19 | E14: content marketing | F14: Content Marketing | G14: E-commerce | H14: Kolkata | I14: New | J14: Completed | K14: 7 | L14: 10.0 | M14: 81200.0 | N14: 16200.0 | O14: 65000.0 | P14: 36200.0 | Q14: 28800.0 | R14: 44.31 | S14: Google | T14: 5600.0 | V14: Social
A15: JSM10014 | B15: C0260 | C15: Client 0260 | D15: 2025-04-19 | E15: Web Designing | F15: Web Design | G15: E-commerce | H15: Chennai | I15: New | J15: Delayed | K15: 6 | L15: 62.0 | M15: 42600.0 | N15: 8500.0 | O15: 34100.0 | P15: 19900.0 | Q15: 14200.0 | R15: 41.64 | S15: Referral | T15: 5400.0 | U15: 4.8 | V15: Direct
A16: JSM10015 | B16: C0307 | C16: Client 0307 | D16: 2025-11-28 | E16: seo | F16: SEO | G16: Hospitality | H16: Pune | I16: New | J16: Completed | K16: 9 | L16: 21.0 | M16: 68300.0 | N16: 3400.0 | O16: 64900.0 | P16: 35700.0 | Q16: 29200.0 | R16: 44.99 | S16: Google | T16: 7300.0 | U16: 3.8 | V16: Paid Search
A17: JSM10016 | B17: C0044 | C17: Client 0044 | D17: 2026-05-13 | E17: SMM | F17: Social Media Marketing | G17: E-commerce | H17: Kolkata | I17: Returning | J17: Cancelled | K17: 3 | L17: 36.0 | M17: 20300.0 | N17: 4100.0 | O17: 16200.0 | P17: 12700.0 | Q17: 3500.0 | R17: 21.6 | S17: Email Campaign | T17: 1000.0 | U17: 4.8 | V17: Paid Search
A18: JSM10017 | B18: C0271 | C18: Client 0271 | D18: 2026-09-14 | E18: Content Marketing | F18: Content Marketing | G18: Real Estate | H18: Hyderabad | I18: New | J18: Cancelled | K18: 8 | L18: 53.0 | M18: 156100.0 | N18: 23400.0 | O18: 132700.0 | P18: 78200.0 | Q18: 54500.0 | R18: 41.07 | S18: Direct | T18: 6700.0 | U18: 3.6 | V18: Social
A19: JSM10018 | B19: C0265 | C19: Client 0265 | D19: 2026-04-08 | E19: Mobile App Development | F19: Mobile App Development | G19: Finance | H19: Mumbai | I19: New | J19: Completed | K19: 3 | L19: 28.0 | M19: 73400.0 | N19: 7300.0 | O19: 66100.0 | P19: 54400.0 | Q19: 11700.0 | R19: 17.7 | S19: Email Campaign | T19: 6500.0 | U19: 4.3 | V19: Direct
A20: JSM10019 | B20: C0302 | C20: Client 0302 | D20: 2025-08-14 | E20: Web Development | F20: Web Development | G20: Real Estate | H20: Delhi NCR | I20: New | J20: Completed | K20: 2 | L20: 31.0 | M20: 67000.0 | N20: 0.0 | O20: 67000.0 | P20: 31400.0 | Q20: 35600.0 | R20: 53.13 | S20: Google | T20: 5700.0 | U20: 3.9 | V20: Social
A21: JSM10020 | B21: C0264 | C21: Client 0264 | D21: 2025-09-01 | E21: SMM | F21: Social Media Marketing | G21: E-commerce | H21: Kolkata | I21: New | J21: Ongoing | K21: 6 | L21: 31.0 | M21: 89400.0 | N21: 17900.0 | O21: 71500.0 | P21: 68300.0 | Q21: 3200.0 | R21: 4.48 | S21: Referral | T21: 8000.0 | U21: 3.9 | V21: Referral
A22: JSM10021 | B22: C0098 | C22: Client 0098 | D22: 2025-04-07 | E22: Online Reputation Management | F22: Online Reputation Management | G22: Manufacturing | H22: Ahmedabad | I22: Returning | J22: Ongoing | K22: 3 | L22: 12.0 | M22: 35200.0 | N22: 3500.0 | O22: 31700.0 | P22: 16500.0 | Q22: 15200.0 | R22: 47.95 | S22: Direct | T22: 2400.0 | U22: 3.8 | V22: Organic Search
A23: JSM10022 | B23: C0032 | C23: Client 0032 | D23: 2026-02-17 | E23: Social Media Marketing | F23: Social Media Marketing | G23: Real Estate | H23: Pune | I23: Returning | J23: Ongoing | K23: 7 | L23: 27.0 | M23: 15000.0 | N23: 0.0 | O23: 15000.0 | P23: 6700.0 | Q23: 8300.0 | R23: 55.33 | S23: Referral | T23: 2600.0 | U23: 4.9 | V23: Direct
A24: JSM10023 | B24: C0072 | C24: Client 0072 | D24: 2026-03-09 | E24: Mobile App Development | F24: Mobile App Development | G24: Education | H24: Kolkata | I24: Returning | J24: Completed | K24: 4 | L24: 37.0 | M24: 17700.0 | N24: 0.0 | O24: 17700.0 | P24: 9600.0 | Q24: 8100.0 | R24: 45.76 | S24: Email Campaign | T24: 3200.0 | U24: 3.8 | V24: Organic Search
A25: JSM10024 | B25: C0334 | C25: Client 0334 | D25: 2026-07-08 | E25: Search Engine Optimization | F25: SEO | G25: E-commerce | H25: Ahmedabad | I25: New | J25: Cancelled | K25: 2 | L25: 36.0 | M25: 87600.0 | N25: 13100.0 | O25: 74500.0 | P25: 60600.0 | Q25: 13900.0 | R25: 18.66 | S25: Direct | T25: 8100.0 | U25: 3.2 | V25: Referral
A26: JSM10025 | B26: C0206 | C26: Client 0206 | D26: 2025-03-02 | E26: Web Development | F26: Web Development | G26: Hospitality | H26: Kolkata | I26: New | J26: Completed | K26: 4 | L26: 58.0 | M26: 67100.0 | N26: 13400.0 | O26: 53700.0 | P26: 34600.0 | Q26: 19100.0 | R26: 35.57 | S26: Social Media | T26: 4900.0 | U26: 5.0 | V26: Referral
... A57: JSM10056 | B57: C0386 | C57: Client 0386 | D57: 2026-02-04 | E57: Content Marketing | F57: Content Marketing | G57: Real Estate | H57: Kolkata | I57: New | J57: Completed | K57: 8 | L57: 70.0 | M57: 50300.0 | N57: 5000.0 | O57: 45300.0 | P57: 37600.0 | Q57: 7700.0 | R57: 17.0 | S57: Referral | T57: 4300.0 | U57: 3.9 | V57: Social
A58: JSM10057 | B58: C0249 | C58: Client 0249 | D58: 2025-01-30 | E58: online reputation management | F58: Online Reputation Management | G58: Manufacturing | H58: Bengaluru | I58: New | J58: Completed | K58: 8 | L58: 43.0 | M58: 31500.0 | O58: 26800.0 | P58: 14100.0 | Q58: 12700.0 | R58: 47.39 | S58: Direct | T58: 4200.0 | U58: 3.7 | V58: Paid Search
A59: JSM10058 | B59: C0202 | C59: Client 0202 | D59: 2026-08-30 | E59: SEO | F59: SEO | G59: E-commerce | H59: Kolkata | I59: New | J59: Completed | K59: 2 | L59: 31.0 | M59: 74900.0 | N59: 7500.0 | O59: 67400.0 | P59: 57700.0 | Q59: 9700.0 | R59: 14.39 | S59: Referral | T59: 6600.0 | U59: 5.0 | V59: Organic Search
A60: JSM10059 | B60: C0195 | C60: Client 0195 | D60: 2025-12-02 | E60: content marketing | F60: Content Marketing | G60: Manufacturing | H60: Hyderabad | I60: New | J60: Completed | K60: 5 | L60: 38.0 | M60: 58200.0 | N60: 2900.0 | O60: 55300.0 | P60: 34300.0 | Q60: 21000.0 | R60: 37.97 | S60: Direct | T60: 9900.0 | U60: 2.9 | V60: Social
A61: JSM10060 | B61: C0241 | C61: Client 0241 | D61: 2025-01-20 | E61: social media marketing | F61: Social Media Marketing | G61: Real Estate | H61: Delhi NCR | I61: New | J61: Completed | K61: 10 | L61: 16.0 | M61: 30700.0 | N61: 4600.0 | O61: 26100.0 | P61: 24300.0 | Q61: 1800.0 | R61: 6.9 | S61: Partner | T61: 1900.0 | U61: 4.9 | V61: Organic Search
A62: JSM10061 | B62: C0127 | C62: Client 0127 | D62: 2025-07-24 | E62: Search Engine Optimization | F62: SEO | G62: E-commerce | H62: Kolkata | I62: Returning | J62: Ongoing | K62: 2 | L62: 58.0 | M62: 71100.0 | N62: 14200.0 | O62: 56900.0 | P62: 36600.0 | Q62: 20300.0 | R62: 35.68 | S62: Partner | T62: 9500.0 | U62: 4.9 | V62: Organic Search
A63: JSM10062 | B63: C0239 | C63: Client 0239 | D63: 2026-12-18 | E63: Web Dev | F63: Web Development | G63: Education | H63: Bengaluru | I63: New | J63: Ongoing | K63: 6 | L63: 38.0 | M63: 64500.0 | N63: 6400.0 | O63: 58100.0 | P63: 37100.0 | Q63: 21000.0 | R63: 36.14 | S63: Social Media | T63: 10100.0 | U63: 3.9 | V63: Organic Search
A64: JSM10063 | B64: C0160 | C64: Client 0160 | D64: 2026-08-13 | E64: Search Engine Optimization | F64: SEO | G64: Education | H64: Pune | I64: Returning | J64: Completed | K64: 8 | L64: 30.0 | M64: 76200.0 | N64: 7600.0 | O64: 68600.0 | P64: 61200.0 | Q64: 7400.0 | R64: 10.79 | S64: Google | T64: 8300.0 | U64: 3.6 | V64: Social
A65: JSM10064 | B65: C0408 | C65: Client 0408 | D65: 2026-08-03 | E65: SMM | F65: Social Media Marketing | G65: Finance | H65: Delhi NCR | I65: New | J65: Completed | K65: 2 | L65: 75.0 | M65: 25500.0 | N65: 2600.0 | O65: 22900.0 | P65: 17600.0 | Q65: 5300.0 | R65: 23.14 | S65: Email Campaign | T65: 3900.0 | U65: 3.3 | V65: Social
A66: JSM10065 | B66: C0216 | C66: Client 0216 | D66: 2026-05-17 | E66: seo | F66: SEO | G66: B2B Services | H66: Bengaluru | I66: New | J66: Completed | K66: 3 | L66: 31.0 | M66: 50900.0 | N66: 0.0 | O66: 50900.0 | P66: 40300.0 | Q66: 10600.0 | R66: 20.83 | S66: Direct | T66: 2400.0 | U66: 2.7 | V66: Paid Search
A67: JSM10066 | B67: C0316 | C67: Client 0316 | D67: 2026-07-06 | E67: Content Marketing | F67: Content Marketing | G67: Hospitality | H67: Chennai | I67: New | J67: Completed | K67: 9 | L67: 69.0 | M67: 37400.0 | N67: 3700.0 | O67: 33700.0 | P67: 17500.0 | Q67: 16200.0 | R67: 48.07 | S67: Referral | T67: 4600.0 | U67: 4.6 | V67: Organic Search
A68: JSM10067 | B68: C0231 | C68: Client 0231 | D68: 2025-09-07 | E68: Content Marketing | F68: Content Marketing | G68: Manufacturing | H68: Chennai | I68: New | J68: Completed | K68: 9 | L68: 39.0 | M68: 46400.0 | N68: 9300.0 | O68: 37100.0 | P68: 35100.0 | Q68: 2000.0 | R68: 5.39 | S68: Google | T68: 5100.0 | U68: 3.8 | V68: Referral
A69: JSM10068 | B69: C0094 | C69: Client 0094 | D69: 2026-05-15 | E69: ppc | F69: PPC | G69: Finance | H69: Hyderabad | I69: Returning | J69: Completed | K69: 5 | L69: 42.0 | M69: 20000.0 | N69: 0.0 | O69: 20000.0 | P69: 14900.0 | Q69: 5100.0 | R69: 25.5 | S69: Email Campaign | T69: 2500.0 | U69: 3.2 | V69: Social
A70: JSM10069 | B70: C0265 | C70: Client 0265 | D70: 2025-07-15 | E70: SEO | F70: SEO | G70: B2B Services | H70: Pune | I70: New | J70: Completed | K70: 3 | L70: 61.0 | M70: 26200.0 | N70: 2600.0 | O70: 23600.0 | P70: 16100.0 | Q70: 7500.0 | R70: 31.78 | S70: Partner | T70: 2800.0 | U70: 4.7 | V70: Referral
... A117: JSM10116 | B117: C0051 | C117: Client 0051 | D117: 2026-12-04 | E117: ppc | F117: PPC | G117: Healthcare | H117: Ahmedabad | I117: Returning | J117: Completed | K117: 7 | L117: 19.0 | M117: 15900.0 | N117: 0.0 | O117: 15900.0 | P117: 11400.0 | Q117: 4500.0 | R117: 28.3 | S117: Social Media | T117: 1200.0 | U117: 3.9 | V117: Paid Search
A118: JSM10117 | B118: C0233 | C118: Client 0233 | D118: 2025-04-04 | E118: Social Media Marketing | F118: Social Media Marketing | G118: Healthcare | I118: New | J118: Ongoing | K118: 5 | L118: 33.0 | M118: 69800.0 | N118: 3500.0 | O118: 66300.0 | P118: 44500.0 | Q118: 21800.0 | R118: 32.88 | S118: Referral | T118: 7700.0 | U118: 2.9 | V118: Paid Search
A119: JSM10118 | B119: C0036 | C119: Client 0036 | D119: 2026-07-22 | E119: Web Dev | F119: Web Development | G119: Finance | H119: Bengaluru | I119: Returning | J119: Completed | K119: 5 | L119: 24.0 | M119: 73400.0 | N119: 11000.0 | O119: 62400.0 | P119: 35700.0 | Q119: 26700.0 | R119: 42.79 | S119: Email Campaign | T119: 6800.0 | U119: 4.8 | V119: Organic Search
A120: JSM10119 | B120: C0075 | C120: Client 0075 | D120: 2025-05-14 | E120: Content Marketing | F120: Content Marketing | G120: Education | H120: Mumbai | I120: Returning | J120: Completed | K120: 10 | L120: 46.0 | M120: 105900.0 | N120: 0.0 | O120: 105900.0 | P120: 86700.0 | Q120: 19200.0 | R120: 18.13 | S120: Referral | T120: 8900.0 | U120: 4.6 | V120: Organic Search
A121: JSM10120 | B121: C0405 | C121: Client 0405 | D121: 2025-09-01 | E121: ppc | F121: PPC | G121: Healthcare | H121: Bengaluru | I121: New | J121: Completed | K121: 7 | L121: 22.0 | M121: 46100.0 | N121: 2300.0 | O121: 43800.0 | P121: 33400.0 | Q121: 10400.0 | R121: 23.74 | S121: Partner | T121: 6400.0 | U121: 3.8 | V121: Referral
A122: JSM10121 | B122: C0382 | C122: Client 0382 | D122: 2025-03-07 | E122: social media marketing | F122: Social Media Marketing | G122: Education | H122: Kolkata | I122: New | J122: Completed | K122: 9 | L122: 39.0 | M122: 26300.0 | N122: -1000.0 | O122: 22400.0 | P122: 15000.0 | Q122: 7400.0 | R122: 33.04 | S122: Email Campaign | T122: 1300.0 | U122: 4.9 | V122: Paid Search
A123: JSM10122 | B123: C0373 | C123: Client 0373 | D123: 2026-11-06 | E123: SEO | F123: SEO | G123: Healthcare | H123: Kolkata | I123: New | J123: Completed | K123: 10 | L123: 29.0 | M123: 35100.0 | N123: 0.0 | O123: 35100.0 | P123: 24900.0 | Q123: 10200.0 | R123: 29.06 | S123: Direct | T123: 1500.0 | U123: 3.7 | V123: Referral
A124: JSM10123 | B124: C0252 | C124: Client 0252 | D124: 2026-12-31 | E124: Social Media Marketing | F124: Social Media Marketing | G124: Finance | H124: Bengaluru | I124: New | J124: Completed | K124: 9 | L124: 61.0 | M124: 133200.0 | N124: 6700.0 | O124: 126500.0 | P124: 94100.0 | Q124: 32400.0 | R124: 25.61 | S124: Google | T124: 11200.0 | U124: 2.9 | V124: Paid Search
A125: JSM10124 | B125: C0320 | C125: Client 0320 | D125: 2026-10-11 | E125: content marketing | F125: Content Marketing | G125: Hospitality | H125: Kolkata | I125: New | J125: Ongoing | K125: 10 | L125: 64.0 | M125: 63600.0 | O125: 54100.0 | P125: 30600.0 | Q125: 23500.0 | R125: 43.44 | S125: Email Campaign | T125: 3200.0 | U125: 4.1 | V125: Direct
A126: JSM10125 | B126: C0051 | C126: Client 0051 | D126: 2026-12-20 | E126: online reputation management | F126: Online Reputation Management | G126: Real Estate | H126: Ahmedabad | I126: Returning | J126: Delayed | K126: 3 | L126: 33.0 | M126: 34800.0 | N126: 1700.0 | O126: 33100.0 | P126: 24700.0 | Q126: 8400.0 | R126: 25.38 | S126: Direct | T126: 5600.0 | U126: 5.0 | V126: Paid Search
A127: JSM10126 | B127: C0174 | C127: Client 0174 | D127: 2026-04-10 | E127: ORM | F127: Online Reputation Management | G127: Finance | H127: Ahmedabad | I127: New | J127: Completed | K127: 8 | L127: 48.0 | M127: 50000.0 | N127: -1000.0 | O127: 45000.0 | P127: 24100.0 | Q127: 20900.0 | R127: 46.44 | S127: Social Media | T127: 4200.0 | U127: 4.4 | V127: Social
A128: JSM10127 | B128: C0079 | C128: Client 0079 | D128: 2026-12-05 | E128: PPC | F128: PPC | G128: Education | H128: ahmedabad | I128: Returning | J128: Completed | K128: 9 | L128: 26.0 | M128: 33800.0 | N128: 0.0 | O128: 33800.0 | P128: 16700.0 | Q128: 17100.0 | R128: 50.59 | S128: Google | T128: 2900.0 | U128: 3.4 | V128: Social
A129: JSM10128 | B129: C0285 | C129: Client 0285 | D129: 2025-03-03 | E129: Web Design | F129: Web Design | G129: Manufacturing | H129: Chennai | I129: New | J129: Completed | K129: 10 | L129: 24.0 | M129: 18600.0 | N129: 0.0 | O129: 18600.0 | P129: 13300.0 | Q129: 5300.0 | R129: 28.49 | S129: Partner | T129: 2800.0 | U129: 5.0 | V129: Referral
A130: JSM10129 | B130: C0148 | C130: Client 0148 | D130: 2026-09-07 | E130: Search Engine Optimization | F130: SEO | G130: E-commerce | H130: Kolkata | I130: Returning | J130: Completed | K130: 6 | L130: 53.0 | M130: 15000.0 | O130: 15000.0 | P130: 11800.0 | Q130: 3200.0 | R130: 21.33 | S130: Referral | T130: 1600.0 | U130: 4.6 | V130: Organic Search
A131: JSM10130 | B131: C0285 | C131: Client 0285 | D131: 2026-01-12 | E131: Pay Per Click | F131: PPC | G131: Manufacturing | I131: New | J131: Ongoing | K131: 3 | L131: 37.0 | M131: 34800.0 | N131: 7000.0 | O131: 27800.0 | P131: 27300.0 | Q131: 500.0 | R131: 1.8 | S131: Email Campaign | T131: 1800.0 | U131: 4.2 | V131: Social
A132: JSM10131 | B132: C0093 | C132: Client 0093 | D132: 2025-10-07 | E132: seo | F132: SEO | G132: Healthcare | H132: Bengaluru | I132: Returning | J132: Delayed | K132: 6 | L132: 5.0 | M132: 43100.0 | N132: 0.0 | O132: 43100.0 | P132: 33900.0 | Q132: 9200.0 | R132: 21.35 | S132: Referral | T132: 6400.0 | U132: 3.5 | V132: Direct
A133: JSM10132 | B133: C0036 | C133: Client 0036 | D133: 2025-05-26 | E133: online reputation management | F133: Online Reputation Management | G133: Real Estate | H133: Ahmedabad | I133: Returning | J133: Completed | K133: 2 | L133: 25.0 | M133: 46300.0 | N133: 0.0 | O133: 46300.0 | P133: 37500.0 | Q133: 8800.0 | R133: 19.01 | S133: Direct | T133: 2800.0 | U133: 3.1 | V133: Referral
A134: JSM10133 | B134: C0081 | C134: Client 0081 | D134: 2026-01-14 | E134: PPC | F134: PPC | G134: Healthcare | H134: Bengaluru | I134: Returning | J134: Ongoing | K134: 6 | L134: 23.0 | M134: 40500.0 | N134: 0.0 | O134: 40500.0 | P134: 33200.0 | Q134: 7300.0 | R134: 18.02 | S134: Referral | T134: 3300.0 | U134: 3.5 | V134: Direct
A135: JSM10134 | B135: C0346 | C135: Client 0346 | D135: 25/03/2025 | E135: SEO | F135: SEO | G135: B2B Services | H135: Kolkata | I135: New | J135: Completed | K135: 6 | L135: 8.0 | M135: 93200.0 | N135: 18600.0 | O135: 74600.0 | P135: 52200.0 | Q135: 22400.0 | R135: 30.03 | S135: Direct | T135: 5000.0 | U135: 3.9 | V135: Social
A136: JSM10135 | B136: C0387 | C136: Client 0387 | D136: 2026-06-09 | E136: Web Development | F136: Web Development | G136: Hospitality | H136: Kolkata | I136: New | J136: Completed | K136: 3 | L136: 37.0 | M136: 32900.0 | N136: 0.0 | O136: 32900.0 | P136: 21300.0 | Q136: 11600.0 | R136: 35.26 | S136: Email Campaign | T136: 2700.0 | U136: 4.3 | V136: Social
A137: JSM10136 | B137: C0113 | C137: Client 0113 | D137: 2026-02-09 | E137: seo | F137: SEO | G137: Real Estate | H137: Bengaluru | I137: Returning | J137: Completed | K137: 2 | L137: 70.0 | M137: 19100.0 | N137: 1000.0 | O137: 18100.0 | P137: 11800.0 | Q137: 6300.0 | R137: 34.81 | S137: Social Media | T137: 1100.0 | U137: 5.0 | V137: Social
A138: JSM10137 | B138: C0062 | C138: Client 0062 | D138: 2025-01-08 | E138: Pay Per Click | F138: PPC | G138: E-commerce | H138: Ahmedabad | I138: Returning | J138: Ongoing | K138: 9 | L138: 43.0 | M138: 38600.0 | N138: 0.0 | O138: 38600.0 | P138: 30800.0 | Q138: 7800.0 | R138: 20.21 | S138: Email Campaign | T138: 3000.0 | U138: 3.4 | V138: Paid Search
A139: JSM10138 | B139: C0037 | C139: Client 0037 | D139: 2026-02-11 | E139: PPC | F139: PPC | G139: Education | H139: Chennai | I139: Returning | J139: Completed | K139: 2 | L139: 69.0 | M139: 74200.0 | N139: 3700.0 | O139: 70500.0 | P139: 32000.0 | Q139: 38500.0 | R139: 54.61 | S139: Email Campaign | T139: 5100.0 | U139: 4.9 | V139: Referral
A140: JSM10139 | B140: C0364 | C140: Client 0364 | D140: 2026-10-18 | E140: Online Reputation Management | F140: Online Reputation Management | G140: Healthcare | H140: Chennai | I140: New | J140: Completed | K140: 8 | L140: 39.0 | M140: 41300.0 | N140: 0.0 | O140: 41300.0 | P140: 20300.0 | Q140: 21000.0 | R140: 50.85 | S140: Referral | T140: 4900.0 | U140: 4.7 | V140: Direct
A141: JSM10140 | B141: C0354 | C141: Client 0354 | D141: 2026-01-06 | E141: Mobile App Development | F141: Mobile App Development | G141: Real Estate | H141: Ahmedabad | I141: New | J141: Completed | K141: 3 | L141: 49.0 | M141: 44700.0 | N141: 4500.0 | O141: 40200.0 | P141: 33200.0 | Q141: 7000.0 | R141: 17.41 | S141: Email Campaign | T141: 6900.0 | U141: 4.1 | V141: Referral
A142: JSM10141 | B142: C0203 | C142: Client 0203 | D142: 2025-11-14 | E142: SMM | F142: Social Media Marketing | G142: Education | H142: Delhi NCR | I142: New | J142: Completed | K142: 7 | L142: 33.0 | M142: 24800.0 | N142: 0.0 | O142: 24800.0 | P142: 13600.0 | Q142: 11200.0 | R142: 45.16 | S142: Email Campaign | T142: 1000.0 | U142: 3.0 | V142: Direct
A143: JSM10142 | B143: C0398 | C143: Client 0398 | D143: 2025-12-24 | E143: Web Dev | F143: Web Development | G143: Real Estate | H143: Delhi NCR | I143: New | J143: Ongoing | K143: 7 | L143: 69.0 | M143: 22400.0 | N143: 2200.0 | O143: 20200.0 | P143: 12800.0 | Q143: 7400.0 | R143: 36.63 | S143: Referral | T143: 3200.0 | U143: 3.6 | V143: Social
A144: JSM10143 | B144: C0089 | C144: Client 0089 | D144: 2026-09-09 | E144: Web Development | F144: Web Development | G144: E-commerce | H144: Kolkata | I144: Returning | J144: Ongoing | K144: 4 | L144: 59.0 | M144: 30700.0 | N144: 4600.0 | O144: 26100.0 | P144: 17300.0 | Q144: 8800.0 | R144: 33.72 | S144: Direct | T144: 2100.0 | U144: 4.7 | V144: Direct
A145: JSM10144 | B145: C0349 | C145: Client 0349 | D145: 2026-08-02 | E145: mobile app development | F145: Mobile App Development | G145: Finance | H145: Bengaluru | I145: New | J145: Delayed | K145: 7 | L145: 37.0 | M145: 36900.0 | N145: 7400.0 | O145: 29500.0 | P145: 15800.0 | Q145: 13700.0 | R145: 46.44 | S145: Direct | T145: 4200.0 | V145: Organic Search
A146: JSM10145 | B146: C0227 | C146: Client 0227 | D146: 2026-10-09 | E146: mobile app development | F146: Mobile App Development | G146: Healthcare | H146: Chennai | I146: New | J146: Ongoing | K146: 6 | L146: 23.0 | M146: 108200.0 | N146: 21600.0 | O146: 86600.0 | P146: 54900.0 | Q146: 31700.0 | R146: 36.61 | S146: Email Campaign | T146: 13600.0 | U146: 4.1 | V146: Organic Search
A147: JSM10146 | B147: C0237 | C147: Client 0237 | D147: 2026-04-08 | E147: content marketing | F147: Content Marketing | G147: Education | H147: Delhi NCR | I147: New | J147: Completed | K147: 2 | L147: 44.0 | M147: 33000.0 | N147: 0.0 | O147: 33000.0 | P147: 14100.0 | Q147: 18900.0 | R147: 57.27 | S147: Email Campaign | T147: 3800.0 | U147: 3.6 | V147: Direct
A148: JSM10147 | B148: C0237 | C148: Client 0237 | D148: 2026-08-18 | E148: online reputation management | F148: Online Reputation Management | G148: Healthcare | H148: Kolkata | I148: New | J148: Cancelled | K148: 10 | L148: 37.0 | M148: 93700.0 | N148: 14100.0 | O148: 79600.0 | P148: 41900.0 | Q148: 37700.0 | R148: 47.36 | S148: Email Campaign | T148: 10400.0 | U148: 3.8 | V148: Paid Search
A149: JSM10148 | B149: C0310 | C149: Client 0310 | D149: 2026-05-03 | E149: PPC | F149: PPC | G149: B2B Services | H149: Delhi NCR | I149: New | J149: Completed | K149: 10 | L149: 47.0 | M149: 108200.0 | N149: 0.0 | O149: 108200.0 | P149: 74200.0 | Q149: 34000.0 | R149: 31.42 | S149: Social Media | T149: 18200.0 | U149: 5.0 | V149: Organic Search
A150: JSM10149 | B150: C0021 | C150: Client 0021 | D150: 2025-09-11 | E150: Web Designing | F150: Web Design | G150: Finance | H150: Chennai | I150: Returning | J150: cancelled | K150: 9 | L150: 5.0 | M150: 21900.0 | N150: 0.0 | O150: 21900.0 | P150: 13700.0 | Q150: 8200.0 | R150: 37.44 | S150: Social Media | T150: 1400.0 | U150: 3.9 | V150: Referral
A151: JSM10150 | B151: C0397 | C151: Client 0397 | D151: 2025-12-13 | E151: online reputation management | F151: Online Reputation Management | G151: Finance | H151: Delhi NCR | I151: New | J151: Ongoing | K151: 2 | L151: 41.0 | M151: 20200.0 | N151: 1000.0 | O151: 19200.0 | P151: 11600.0 | Q151: 7600.0 | R151: 39.58 | S151: Social Media | T151: 1700.0 | U151: 4.5 | V151: Organic Search
A152: JSM10151 | B152: C0146 | C152: Client 0146 | D152: 2025-09-16 | E152: online reputation management | F152: Online Reputation Management | G152: E-commerce | H152: Chennai | I152: Returning | J152: Completed | K152: 4 | L152: 20.0 | M152: 79200.0 | N152: 0.0 | O152: 79200.0 | P152: 51200.0 | Q152: 28000.0 | R152: 35.35 | S152: Social Media | T152: 7600.0 | U152: 3.0 | V152: Referral
A153: JSM10152 | B153: C0305 | C153: Client 0305 | D153: 2026-12-27 | E153: Web Design | F153: Web Design | G153: Finance | H153: Bengaluru | I153: New | J153: Completed | K153: 3 | L153: 35.0 | M153: 22500.0 | N153: 0.0 | O153: 22500.0 | P153: 17000.0 | Q153: 5500.0 | R153: 24.44 | S153: Partner | T153: 2500.0 | U153: 4.2 | V153: Direct
A154: JSM10153 | B154: C0331 | C154: Client 0331 | D154: 2026-11-18 | E154: Social Media Marketing | F154: Social Media Marketing | G154: Finance | H154: Hyderabad | I154: New | J154: Completed | K154: 8 | L154: 7.0 | M154: 76300.0 | N154: 11400.0 | O154: 64900.0 | P154: 55600.0 | Q154: 9300.0 | R154: 14.33 | S154: Referral | T154: 5700.0 | U154: 3.4 | V154: Paid Search
A155: JSM10154 | B155: C0393 | C155: Client 0393 | D155: 2026-05-13 | E155: Pay Per Click | F155: PPC | G155: E-commerce | H155: Delhi NCR | I155: New | J155: Completed | K155: 5 | L155: 5.0 | M155: 67700.0 | N155: 3400.0 | O155: 64300.0 | P155: 40900.0 | Q155: 23400.0 | R155: 36.39 | S155: Social Media | T155: 9900.0 | V155: Organic Search
A156: JSM10155 | B156: C0339 | C156: Client 0339 | D156: 2025-12-11 | E156: Search Engine Optimization | F156: SEO | G156: E-commerce | H156: Bengaluru | I156: New | J156: Completed | K156: 4 | L156: 49.0 | M156: 75700.0 | N156: 0.0 | O156: 75700.0 | P156: 40000.0 | Q156: 35700.0 | R156: 47.16 | S156: Partner | T156: 4100.0 | U156: 4.7 | V156: Direct
A157: JSM10156 | B157: C0370 | C157: Client 0370 | D157: 2026-03-25 | E157: Web Designing | F157: Web Design | G157: B2B Services | H157: Hyderabad | I157: New | J157: Completed | K157: 2 | L157: 27.0 | M157: 50000.0 | N157: 2500.0 | O157: 47500.0 | P157: 22700.0 | Q157: 24800.0 | R157: 52.21 | S157: Partner | T157: 6800.0 | U157: 5.0 | V157: Referral
A158: JSM10157 | B158: C0274 | C158: Client 0274 | D158: 2025-09-02 | E158: Web Development | F158: Web Development | G158: Real Estate | H158: Chennai | I158: New | J158: Cancelled | K158: 6 | L158: 48.0 | M158: 80400.0 | N158: 16100.0 | O158: 64300.0 | P158: 56000.0 | Q158: 8300.0 | R158: 12.91 | S158: Partner | T158: 11400.0 | U158: 4.3 | V158: Direct
A159: JSM10158 | B159: C0237 | C159: Client 0237 | D159: 2025-10-16 | E159: Mobile App Dev | F159: Mobile App Development | G159: E-commerce | H159: Pune | I159: New | J159: Completed | K159: 8 | L159: 51.0 | M159: 38000.0 | N159: 0.0 | O159: 38000.0 | P159: 26100.0 | Q159: 11900.0 | R159: 31.32 | S159: Email Campaign | T159: 4600.0 | U159: 4.2 | V159: Paid Search
A160: JSM10159 | B160: C0027 | C160: Client 0027 | D160: 2026-10-19 | E160: Content Marketing | F160: Content Marketing | G160: Education | H160: Delhi NCR | I160: Returning | J160: Delayed | K160: 9 | L160: 5.0 | M160: 38000.0 | N160: 0.0 | O160: 38000.0 | P160: 17800.0 | Q160: 20200.0 | R160: 53.16 | S160: Social Media | T160: 2500.0 | U160: 4.0 | V160: Organic Search
A161: JSM10160 | B161: C0140 | C161: Client 0140 | D161: 2026-04-06 | E161: Web Design | F161: Web Design | G161: Education | H161: Pune | I161: Returning | J161: Completed | K161: 10 | L161: 20.0 | M161: 63700.0 | N161: 3200.0 | O161: 60500.0 | P161: 28200.0 | Q161: 32300.0 | R161: 53.39 | S161: Direct | T161: 5100.0 | U161: 4.6 | V161: Social
A162: JSM10161 | B162: C0213 | C162: Client 0213 | D162: 2025-02-24 | E162: Search Engine Optimization | F162: SEO | G162: Manufacturing | H162: Delhi NCR | I162: New | J162: Completed | K162: 8 | L162: 12.0 | M162: 58400.0 | N162: 0.0 | O162: 58400.0 | P162: 27300.0 | Q162: 31100.0 | R162: 53.25 | S162: Social Media | T162: 9600.0 | U162: 2.5 | V162: Paid Search
A163: JSM10162 | B163: C0164 | C163: Client 0164 | D163: 2025-04-12 | E163: Search Engine Optimization | F163: SEO | G163: Healthcare | H163: Hyderabad | I163: Returning | J163: Ongoing | K163: 7 | L163: 61.0 | M163: 98200.0 | N163: 9800.0 | O163: 88400.0 | P163: 72800.0 | Q163: 15600.0 | R163: 17.65 | S163: Direct | T163: 13300.0 | U163: 2.9 | V163: Paid Search
A164: JSM10163 | B164: C0230 | C164: Client 0230 | D164: 2026-09-23 | E164: Mobile App Development | F164: Mobile App Development | G164: Hospitality | H164: Pune | I164: New | J164: Delayed | K164: 2 | L164: 56.0 | M164: 19600.0 | N164: 0.0 | O164: 19600.0 | P164: 15200.0 | Q164: 4400.0 | R164: 22.45 | S164: Referral | T164: 3200.0 | U164: 3.4 | V164: Direct
A165: JSM10164 | B165: C0057 | C165: Client 0057 | D165: 2025-10-23 | E165: ORM | F165: Online Reputation Management | G165: Real Estate | H165: Ahmedabad | I165: Returning | J165: Completed | K165: 5 | L165: 5.0 | M165: 34900.0 | N165: 1700.0 | O165: 33200.0 | P165: 27700.0 | Q165: 5500.0 | R165: 16.57 | S165: Partner | T165: 6000.0 | U165: 3.3 | V165: Direct
A166: JSM10165 | B166: C0033 | C166: Client 0033 | D166: 2025-04-24 | E166: Mobile App Development | F166: Mobile App Development | G166: Real Estate | H166: Bengaluru | I166: Returning | J166: Completed | K166: 9 | L166: 60.0 | M166: 30500.0 | N166: 4600.0 | O166: 25900.0 | P166: 17700.0 | Q166: 8200.0 | R166: 31.66 | S166: Social Media | T166: 2800.0 | U166: 3.1 | V166: Referral
A167: JSM10166 | B167: C0315 | C167: Client 0315 | D167: 2025-12-28 | E167: Search Engine Optimization | F167: SEO | G167: Education | H167: Chennai | I167: New | J167: Completed | K167: 5 | L167: 48.0 | M167: 28500.0 | N167: 2800.0 | O167: 25700.0 | P167: 15800.0 | Q167: 9900.0 | R167: 38.52 | S167: Google | T167: 3700.0 | U167: 4.0 | V167: Direct
... A201: JSM10200 | B201: C0407 | C201: Client 0407 | D201: 2025-12-14 | E201: Pay Per Click | F201: PPC | G201: Real Estate | H201: Ahmedabad | I201: New | J201: Delayed | K201: 10 | L201: 39.0 | M201: 20700.0 | N201: 0.0 | O201: 20700.0 | P201: 16800.0 | Q201: 3900.0 | R201: 18.84 | S201: Email Campaign | T201: 2800.0 | U201: 3.4 | V201: Organic Search
A202: JSM10201 | B202: C0020 | C202: Client 0020 | D202: 2025-05-21 | E202: SEO | F202: SEO | G202: E-commerce | H202: Bengaluru | I202: Returning | J202: Ongoing | K202: 7 | M202: 60800.0 | N202: 0.0 | O202: 60800.0 | P202: 29600.0 | Q202: 31200.0 | R202: 51.32 | S202: Social Media | T202: 10500.0 | U202: 5.0 | V202: Direct
A203: JSM10202 | B203: C0084 | C203: Client 0084 | D203: 2026-02-07 | E203: PPC | F203: PPC | G203: Hospitality | H203: Kolkata | I203: Returning | J203: Completed | K203: 6 | L203: 62.0 | M203: 19100.0 | N203: 0.0 | O203: 19100.0 | P203: 15200.0 | Q203: 3900.0 | R203: 20.42 | S203: Google | T203: 2400.0 | U203: 4.7 | V203: Social
A204: JSM10203 | B204: C0345 | C204: Client 0345 | D204: 2025-04-23 | E204: PPC | F204: PPC | G204: B2B Services | H204: Hyderabad | I204: New | J204: Completed | K204: 8 | L204: 47.0 | M204: 91100.0 | N204: 4600.0 | O204: 86500.0 | P204: 55900.0 | Q204: 30600.0 | R204: 35.38 | S204: Partner | T204: 14300.0 | U204: 5.0 | V204: Direct
A205: JSM10204 | B205: C0370 | C205: Client 0370 | D205: 2025-02-22 | E205: Web Development | F205: Web Development | G205: E-commerce | H205: Pune | I205: New | J205: Completed | K205: 9 | L205: 41.0 | M205: 138900.0 | N205: 0.0 | O205: 138900.0 | P205: 87600.0 | Q205: 51300.0 | R205: 36.93 | S205: Google | T205: 14100.0 | U205: 3.7 | V205: Direct
A206: JSM10205 | B206: C0098 | C206: Client 0098 | D206: 2025-01-20 | E206: SMM | F206: Social Media Marketing | G206: Manufacturing | H206: Pune | I206: Returning | J206: Completed | K206: 9 | L206: 49.0 | M206: 105000.0 | N206: 0.0 | O206: 105000.0 | P206: 71400.0 | Q206: 33600.0 | R206: 32.0 | S206: Direct | T206: 17000.0 | U206: 3.4 | V206: Direct
A207: JSM10206 | B207: C0377 | C207: Client 0377 | D207: 2025-03-05 | E207: mobile app development | F207: Mobile App Development | G207: Finance | H207: Kolkata | I207: New | J207: Completed | K207: 4 | L207: 28.0 | M207: 62300.0 | N207: 0.0 | O207: 62300.0 | P207: 38600.0 | Q207: 23700.0 | R207: 38.04 | S207: Email Campaign | T207: 2700.0 | U207: 4.8 | V207: Referral
A208: JSM10207 | B208: C0089 | C208: Client 0089 | D208: 2026-04-16 | E208: ppc | F208: PPC | G208: Hospitality | H208: Kolkata | I208: Returning | J208: Completed | K208: 10 | L208: 14.0 | M208: 85700.0 | N208: 4300.0 | O208: 81400.0 | P208: 54600.0 | Q208: 26800.0 | R208: 32.92 | S208: Referral | T208: 10700.0 | U208: 4.5 | V208: Paid Search
A209: JSM10208 | B209: C0286 | C209: Client 0286 | D209: 2025-11-02 | E209: content marketing | F209: Content Marketing | G209: Hospitality | H209: Pune | I209: New | J209: Delayed | K209: 5 | L209: 19.0 | M209: 38500.0 | N209: 0.0 | O209: 38500.0 | P209: 29500.0 | Q209: 9000.0 | R209: 23.38 | S209: Partner | T209: 5500.0 | U209: 3.0 | V209: Referral
...

Sheet Cleaned_Data
A1: Project_ID | B1: Client_ID | C1: Client_Name | D1: Project_Date | E1: Service | F1: Service_Category | G1: Industry | H1: Region | I1: Client_Type | J1: Project_Status | K1: Team_Size | L1: Project_Duration_Days | M1: Quoted_Value | N1: Discount | O1: Revenue | P1: Project_Cost | Q1: Profit | R1: Profit_Margin_Pct | S1: Lead_Source | T1: Marketing_Spend | U1: Customer_Rating | V1: Acquisition_Channel
A2: JSM10088 | B2: C0264 | C2: Client 0264 | D2: 45659 | E2: Online Reputation Management | F2: Online Reputation Management | G2: Real Estate | H2: Chennai | I2: New | J2: Completed | K2: 10 | L2: 68 | M2: 71400 | N2: 0 | O2: 71400 | P2: 38500 | Q2: 32900 | R2: 46.08 | S2: Email Campaign | T2: 11500 | U2: 4 | V2: Referral
A3: JSM10700 | B3: C0014 | C3: Client 0014 | D3: 45660 | E3: Web Development | F3: Web Development | G3: Education | H3: Hyderabad | I3: Returning | J3: Completed | K3: 4 | L3: 41 | M3: 88400 | N3: 17700 | O3: 70700 | P3: 52300 | Q3: 18400 | R3: 26.03 | S3: Direct | T3: 11900 | U3: 4.4 | V3: Paid Search
A4: JSM10034 | B4: C0023 | C4: Client 0023 | D4: 45661 | E4: Content Marketing | F4: Content Marketing | G4: Hospitality | H4: Bengaluru | I4: Returning | J4: Ongoing | K4: 7 | L4: 52 | M4: 83900 | N4: 4200 | O4: 79700 | P4: 57000 | Q4: 22700 | R4: 28.48 | S4: Partner | T4: 10500 | U4: 3.6 | V4: Referral
A5: JSM10392 | B5: C0347 | C5: Client 0347 | D5: 45662 | E5: SEO | F5: SEO | G5: Hospitality | H5: Bengaluru | I5: New | J5: Completed | K5: 5 | M5: 141500 | N5: 0 | O5: 141500 | P5: 92100 | Q5: 49400 | R5: 34.91 | S5: Google | T5: 5800 | U5: 4.6 | V5: Referral
A6: JSM10418 | B6: C0256 | C6: Client 0256 | D6: 45662 | E6: Web Design | F6: Web Design | G6: B2B Services | H6: Bengaluru | I6: New | J6: Ongoing | K6: 10 | L6: 71 | M6: 61400 | N6: 3100 | O6: 58300 | P6: 47400 | Q6: 10900 | R6: 18.7 | S6: Partner | T6: 2500 | U6: 5 | V6: Direct
A7: JSM11149 | B7: C0344 | C7: Client 0344 | D7: 45664 | E7: Online Reputation Management | F7: Online Reputation Management | G7: B2B Services | H7: Mumbai | I7: New | J7: Ongoing | K7: 9 | L7: 15 | M7: 75200 | N7: 11300 | O7: 63900 | P7: 45400 | Q7: 18500 | R7: 28.95 | S7: Google | T7: 6400 | U7: 4.3 | V7: Organic Search
A8: JSM10539 | B8: C0155 | C8: Client 0155 | D8: 45664 | E8: Web Design | F8: Web Design | G8: Finance | H8: Mumbai | I8: Returning | J8: Cancelled | K8: 6 | L8: 36 | M8: 34600 | N8: 3500 | O8: 31100 | P8: 15700 | Q8: 15400 | R8: 49.52 | S8: Partner | T8: 5100 | U8: 4.3 | V8: Social
A9: JSM10811 | B9: C0394 | C9: Client 0394 | D9: 45664 | E9: Online Reputation Management | F9: Online Reputation Management | G9: Finance | H9: Hyderabad | I9: New | J9: Ongoing | K9: 5 | L9: 5 | M9: 33400 | N9: 6700 | O9: 26700 | P9: 26900 | Q9: -200 | R9: -0.75 | S9: Email Campaign | T9: 3600 | U9: 3.5 | V9: Paid Search
A10: JSM10440 | B10: C0274 | C10: Client 0274 | D10: 45664 | E10: Social Media Marketing | F10: Social Media Marketing | G10: Education | H10: Chennai | I10: New | J10: Ongoing | K10: 3 | L10: 73 | M10: 60000 | N10: 3000 | O10: 57000 | P10: 43400 | Q10: 13600 | R10: 23.86 | S10: Email Campaign | T10: 3400 | U10: 5 | V10: Organic Search
A11: JSM10003 | B11: C0415 | C11: Client 0415 | D11: 45664 | E11: Content Marketing | F11: Content Marketing | G11: Hospitality | H11: Bengaluru | I11: New | J11: Ongoing | K11: 4 | L11: 27 | M11: 33200 | N11: 3300 | O11: 29900 | P11: 16400 | Q11: 13500 | R11: 45.15 | S11: Referral | T11: 3800 | U11: 2.5 | V11: Social
A12: JSM10902 | B12: C0104 | C12: Client 0104 | D12: 45665 | E12: Content Marketing | F12: Content Marketing | G12: Real Estate | H12: Chennai | I12: Returning | J12: Completed | K12: 4 | L12: 32 | M12: 83300 | N12: 8300 | O12: 75000 | P12: 35200 | Q12: 39800 | R12: 53.07 | S12: Email Campaign | T12: 10500 | U12: 2.3 | V12: Referral
A13: JSM10137 | B13: C0062 | C13: Client 0062 | D13: 45665 | E13: PPC | F13: PPC | G13: E-commerce | H13: Ahmedabad | I13: Returning | J13: Ongoing | K13: 9 | L13: 43 | M13: 38600 | N13: 0 | O13: 38600 | P13: 30800 | Q13: 7800 | R13: 20.21 | S13: Email Campaign | T13: 3000 | U13: 3.4 | V13: Paid Search
A14: JSM11301 | B14: C0077 | C14: Client 0077 | D14: 45665 | E14: Social Media Marketing | F14: Social Media Marketing | G14: Real Estate | H14: Kolkata | I14: Returning | J14: Delayed | K14: 7 | L14: 40 | M14: 65400 | N14: 9800 | O14: 55600 | P14: 41600 | Q14: 14000 | R14: 25.18 | S14: Direct | T14: 3900 | U14: 2.6 | V14: Organic Search
A15: JSM11252 | B15: C0205 | C15: Client 0205 | D15: 45667 | E15: Online Reputation Management | F15: Online Reputation Management | G15: Hospitality | H15: Chennai | I15: New | J15: Completed | K15: 6 | L15: 13 | M15: 45100 | N15: 4500 | O15: 40600 | P15: 35300 | Q15: 5300 | R15: 13.05 | S15: Email Campaign | T15: 4000 | U15: 4.4 | V15: Social
A16: JSM10035 | B16: C0288 | C16: Client 0288 | D16: 45667 | E16: Online Reputation Management | F16: Online Reputation Management | G16: E-commerce | H16: Mumbai | I16: New | J16: Completed | K16: 3 | L16: 22 | M16: 48100 | N16: 9600 | O16: 38500 | P16: 27300 | Q16: 11200 | R16: 29.09 | S16: Social Media | T16: 2900 | U16: 4 | V16: Direct
A17: JSM10216 | B17: C0020 | C17: Client 0020 | D17: 45667 | E17: Content Marketing | F17: Content Marketing | G17: Finance | H17: Hyderabad | I17: Returning | J17: Completed | K17: 6 | L17: 33 | M17: 15000 | N17: 0 | O17: 15000 | P17: 11300 | Q17: 3700 | R17: 24.67 | S17: Direct | T17: 1500 | U17: 4.3 | V17: Direct
... A26: JSM11117 | B26: C0109 | C26: Client 0109 | D26: 45671 | E26: SEO | F26: SEO | G26: Real Estate | H26: Kolkata | I26: Returning | J26: Completed | K26: 5 | L26: 38 | M26: 38300 | N26: 5700 | O26: 32600 | P26: 31000 | Q26: 1600 | R26: 4.91 | S26: Google | T26: 1900 | U26: 4.5 | V26: Social
A27: JSM11462 | B27: C0292 | C27: Client 0292 | D27: 45672 | E27: SEO | F27: SEO | G27: E-commerce | H27: Chennai | I27: New | J27: Completed | K27: 4 | L27: 33 | M27: 15000 | N27: 3000 | O27: 12000 | P27: 10600 | Q27: 1400 | R27: 11.67 | S27: Direct | T27: 1300 | V27: Paid Search
A28: JSM10074 | B28: C0155 | C28: Client 0155 | D28: 45672 | E28: Web Design | F28: Web Design | G28: Healthcare | H28: Hyderabad | I28: Returning | J28: Completed | K28: 10 | L28: 20 | M28: 97800 | N28: 0 | O28: 97800 | P28: 76900 | Q28: 20900 | R28: 21.37 | S28: Partner | T28: 16900 | U28: 3.6 | V28: Paid Search
A29: JSM10991 | B29: C0208 | C29: Client 0208 | D29: 45672 | E29: Social Media Marketing | F29: Social Media Marketing | G29: Manufacturing | H29: Chennai | I29: New | J29: Delayed | K29: 5 | L29: 52 | M29: 63500 | N29: 6400 | O29: 57100 | P29: 33500 | Q29: 23600 | R29: 41.33 | S29: Referral | T29: 6000 | U29: 3.3 | V29: Direct
A30: JSM11181 | B30: C0411 | C30: Client 0411 | D30: 45673 | E30: SEO | F30: SEO | G30: Healthcare | H30: Bengaluru | I30: New | J30: Ongoing | K30: 5 | L30: 19 | M30: 100000 | N30: 0 | O30: 100000 | P30: 47800 | Q30: 52200 | R30: 52.2 | S30: Direct | T30: 16600 | U30: 4.1 | V30: Paid Search
A31: JSM11241 | B31: C0011 | C31: Client 0011 | D31: 45673 | E31: Online Reputation Management | F31: Online Reputation Management | G31: Education | H31: Ahmedabad | I31: Returning | J31: Completed | K31: 10 | L31: 55 | M31: 17000 | N31: 800 | O31: 16200 | P31: 10200 | Q31: 6000 | R31: 37.04 | S31: Referral | T31: 1600 | U31: 3.8 | V31: Direct
A32: JSM10465 | B32: C0056 | C32: Client 0056 | D32: 45674 | E32: Web Design | F32: Web Design | G32: E-commerce | H32: Delhi Ncr | I32: Returning | J32: Completed | K32: 5 | L32: 30 | M32: 40500 | N32: 4000 | O32: 36500 | P32: 23100 | Q32: 13400 | R32: 36.71 | S32: Referral | T32: 6500 | U32: 4.6 | V32: Referral
A33: JSM10795 | B33: C0418 | C33: Client 0418 | D33: 45674 | E33: Social Media Marketing | F33: Social Media Marketing | G33: B2B Services | H33: Bengaluru | I33: New | J33: Delayed | K33: 5 | L33: 46 | M33: 49400 | N33: 9900 | O33: 39500 | P33: 32100 | Q33: 7400 | R33: 18.73 | S33: Partner | T33: 5800 | U33: 4.7 | V33: Paid Search
A34: JSM10914 | B34: C0047 | C34: Client 0047 | D34: 45674 | E34: Web Development | F34: Web Development | G34: Finance | H34: Pune | I34: Returning | J34: Completed | K34: 8 | L34: 56 | M34: 39700 | N34: 2000 | O34: 37700 | P34: 18300 | Q34: 19400 | R34: 51.46 | S34: Partner | T34: 3300 | U34: 4.5 | V34: Organic Search
A35: JSM11121 | B35: C0124 | C35: Client 0124 | D35: 45674 | E35: Social Media Marketing | F35: Social Media Marketing | G35: B2B Services | H35: Kolkata | I35: Returning | J35: Completed | K35: 9 | L35: 87 | M35: 18900 | N35: 1900 | O35: 17000 | P35: 9200 | Q35: 7800 | R35: 45.88 | S35: Social Media | T35: 2700 | U35: 4 | V35: Social
A36: JSM10070 | B36: C0230 | C36: Client 0230 | D36: 45675 | E36: Mobile App Development | F36: Mobile App Development | G36: Real Estate | H36: Hyderabad | I36: New | J36: Completed | K36: 3 | L36: 35 | M36: 43900 | N36: 4400 | O36: 39500 | P36: 18600 | Q36: 20900 | R36: 52.91 | S36: Partner | T36: 4700 | U36: 3.4 | V36: Direct
A37: JSM10060 | B37: C0241 | C37: Client 0241 | D37: 45677 | E37: Social Media Marketing | F37: Social Media Marketing | G37: Real Estate | H37: Delhi Ncr | I37: New | J37: Completed | K37: 10 | L37: 16 | M37: 30700 | N37: 4600 | O37: 26100 | P37: 24300 | Q37: 1800 | R37: 6.9 | S37: Partner | T37: 1900 | U37: 4.9 | V37: Organic Search
A38: JSM10650 | B38: C0335 | C38: Client 0335 | D38: 45677 | E38: Mobile App Development | F38: Mobile App Development | G38: Healthcare | H38: Pune | I38: New | J38: Delayed | K38: 9 | L38: 44 | M38: 37700 | N38: 1900 | O38: 35800 | P38: 30400 | Q38: 5400 | R38: 15.08 | S38: Partner | T38: 3800 | U38: 3.9 | V38: Paid Search
A39: JSM10205 | B39: C0098 | C39: Client 0098 | D39: 45677 | E39: Social Media Marketing | F39: Social Media Marketing | G39: Manufacturing | H39: Pune | I39: Returning | J39: Completed | K39: 9 | L39: 49 | M39: 105000 | N39: 0 | O39: 105000 | P39: 71400 | Q39: 33600 | R39: 32 | S39: Direct | T39: 17000 | U39: 3.4 | V39: Direct
... A126: JSM10860 | B126: C0160 | C126: Client 0160 | D126: 45722 | E126: PPC | F126: PPC | G126: Healthcare | H126: Chennai | I126: Returning | J126: Completed | K126: 3 | L126: 12 | M126: 51500 | N126: 2600 | O126: 48900 | P126: 39700 | Q126: 9200 | R126: 18.81 | S126: Social Media | T126: 5600 | U126: 3.7 | V126: Paid Search
A127: JSM10265 | B127: C0075 | C127: Client 0075 | D127: 45722 | E127: Mobile App Development | F127: Mobile App Development | G127: Hospitality | H127: Kolkata | I127: Returning | J127: Completed | K127: 4 | M127: 59400 | N127: 5900 | O127: 53500 | P127: 47900 | Q127: 5600 | R127: 10.47 | S127: Google | T127: 4500 | U127: 2.2 | V127: Social
A128: JSM10121 | B128: C0382 | C128: Client 0382 | D128: 45723 | E128: Social Media Marketing | F128: Social Media Marketing | G128: Education | H128: Kolkata | I128: New | J128: Completed | K128: 9 | L128: 39 | M128: 26300 | N128: 0 | O128: 26300 | P128: 15000 | Q128: 11300 | R128: 42.97 | S128: Email Campaign | T128: 1300 | U128: 4.9 | V128: Paid Search
A129: JSM11434 | B129: C0315 | C129: Client 0315 | D129: 45723 | E129: Social Media Marketing | F129: Social Media Marketing | G129: Real Estate | H129: Pune | I129: New | J129: Completed | K129: 10 | L129: 18 | M129: 131700 | N129: 0 | O129: 131700 | P129: 88700 | Q129: 43000 | R129: 32.65 | S129: Email Campaign | T129: 6100 | U129: 4.1 | V129: Paid Search
A130: JSM10012 | B130: C0306 | C130: Client 0306 | D130: 45723 | E130: Online Reputation Management | F130: Online Reputation Management | G130: Hospitality | H130: Mumbai | I130: New | J130: Completed | K130: 8 | L130: 50 | M130: 65100 | N130: 6500 | O130: 58600 | P130: 44300 | Q130: 14300 | R130: 24.4 | S130: Partner | T130: 9400 | U130: 4.2 | V130: Organic Search
A131: JSM10182 | B131: C0364 | C131: Client 0364 | D131: 45724 | E131: PPC | F131: PPC | G131: E-commerce | H131: Bengaluru | I131: New | J131: Completed | K131: 10 | L131: 53 | M131: 63500 | N131: 0 | O131: 63500 | P131: 29600 | Q131: 33900 | R131: 53.39 | S131: Social Media | T131: 8200 | U131: 2.9 | V131: Direct
A132: JSM10076 | B132: C0059 | C132: Client 0059 | D132: 45724 | E132: Mobile App Development | F132: Mobile App Development | G132: Healthcare | H132: Bengaluru | I132: Returning | J132: Completed | K132: 8 | L132: 28 | M132: 29200 | N132: 1500 | O132: 27700 | P132: 23600 | Q132: 4100 | R132: 14.8 | S132: Referral | T132: 3800 | U132: 4.2 | V132: Direct
A133: JSM10393 | B133: C0086 | C133: Client 0086 | D133: 45724 | E133: Content Marketing | F133: Content Marketing | G133: B2B Services | H133: Chennai | I133: Returning | J133: Completed | K133: 2 | L133: 25 | M133: 53400 | N133: 5300 | O133: 48100 | P133: 40400 | Q133: 7700 | R133: 16.01 | S133: Direct | T133: 6700 | U133: 3.1 | V133: Paid Search
A134: JSM10734 | B134: C0353 | C134: Client 0353 | D134: 45725 | E134: Social Media Marketing | F134: Social Media Marketing | G134: Healthcare | H134: Chennai | I134: New | J134: Completed | K134: 6 | L134: 23 | M134: 47600 | N134: 0 | O134: 47600 | P134: 33500 | Q134: 14100 | R134: 29.62 | S134: Google | T134: 2600 | U134: 4 | V134: Referral
A135: JSM10009 | B135: C0138 | C135: Client 0138 | D135: 45725 | E135: Online Reputation Management | F135: Online Reputation Management | G135: Finance | H135: Pune | I135: Returning | J135: Delayed | K135: 5 | L135: 19 | M135: 18600 | N135: 2800 | O135: 15800 | P135: 9800 | Q135: 6000 | R135: 37.97 | S135: Partner | T135: 1900 | U135: 4.2 | V135: Referral
A136: JSM11170 | B136: C0411 | C136: Client 0411 | D136: 45726 | E136: Web Design | F136: Web Design | G136: Education | H136: Delhi Ncr | I136: New | J136: Completed | K136: 9 | L136: 40 | M136: 70800 | N136: 0 | O136: 70800 | P136: 32900 | Q136: 37900 | R136: 53.53 | S136: Referral | T136: 5700 | U136: 4.9 | V136: Direct
A137: JSM11255 | B137: C0241 | C137: Client 0241 | D137: 45726 | E137: Web Design | F137: Web Design | G137: Real Estate | H137: Delhi Ncr | I137: New | J137: Completed | K137: 2 | L137: 64 | M137: 77400 | N137: 15500 | O137: 61900 | P137: 36400 | Q137: 25500 | R137: 41.2 | S137: Email Campaign | T137: 10900 | U137: 3.5 | V137: Referral
A138: JSM10365 | B138: C0164 | C138: Client 0164 | D138: 45726 | E138: Content Marketing | F138: Content Marketing | G138: Finance | H138: Hyderabad | I138: Returning | J138: Completed | K138: 3 | L138: 17 | M138: 47100 | N138: 9400 | O138: 37700 | P138: 20000 | Q138: 17700 | R138: 46.95 | S138: Email Campaign | T138: 4300 | U138: 3.6 | V138: Referral
A139: JSM11368 | B139: C0325 | C139: Client 0325 | D139: 45726 | E139: PPC | F139: PPC | G139: E-commerce | H139: Delhi Ncr | I139: New | J139: Completed | K139: 3 | L139: 28 | M139: 22400 | N139: 4500 | O139: 17900 | P139: 12000 | Q139: 5900 | R139: 32.96 | S139: Email Campaign | T139: 2700 | U139: 4.8 | V139: Referral
... A194: JSM10862 | B194: C0392 | C194: Client 0392 | D194: 45755 | E194: Mobile App Development | F194: Mobile App Development | G194: Healthcare | H194: Mumbai | I194: New | J194: Completed | K194: 9 | L194: 29 | M194: 36100 | N194: 0 | O194: 36100 | P194: 16000 | Q194: 20100 | R194: 55.68 | S194: Direct | T194: 3800 | U194: 5 | V194: Social
A195: JSM11109 | B195: C0241 | C195: Client 0241 | D195: 45755 | E195: Social Media Marketing | F195: Social Media Marketing | G195: Finance | H195: Chennai | I195: New | J195: Ongoing | K195: 8 | M195: 71700 | N195: 3600 | O195: 68100 | P195: 51600 | Q195: 16500 | R195: 24.23 | S195: Direct | T195: 3700 | U195: 4.2 | V195: Organic Search
A196: JSM11395 | B196: C0340 | C196: Client 0340 | D196: 45756 | E196: Mobile App Development | F196: Mobile App Development | G196: Education | H196: Chennai | I196: New | J196: Ongoing | K196: 7 | L196: 39 | M196: 37700 | N196: 1900 | O196: 35800 | P196: 19900 | Q196: 15900 | R196: 44.41 | S196: Direct | T196: 2000 | U196: 3.5 | V196: Organic Search
A197: JSM11479 | B197: C0347 | C197: Client 0347 | D197: 45757 | E197: SEO | F197: SEO | G197: Healthcare | H197: Chennai | I197: New | J197: Completed | K197: 3 | L197: 19 | M197: 88900 | N197: 17800 | O197: 71100 | P197: 48400 | Q197: 22700 | R197: 31.93 | S197: Google | T197: 9300 | U197: 5 | V197: Social
A198: JSM10534 | B198: C0266 | C198: Client 0266 | D198: 45757 | E198: Web Development | F198: Web Development | G198: Real Estate | H198: Pune | I198: New | J198: Ongoing | K198: 3 | L198: 57 | M198: 49600 | N198: 2500 | O198: 47100 | P198: 21900 | Q198: 25200 | R198: 53.5 | S198: Email Campaign | T198: 6500 | U198: 4.5 | V198: Paid Search
A199: JSM11441 | B199: C0177 | C199: Client 0177 | D199: 45757 | E199: Web Development | F199: Web Development | G199: B2B Services | H199: Bengaluru | I199: New | J199: Completed | K199: 4 | L199: 37 | M199: 106300 | N199: 5300 | O199: 101000 | P199: 82100 | Q199: 18900 | R199: 18.71 | S199: Email Campaign | T199: 7800 | U199: 5 | V199: Paid Search
A200: JSM11143 | B200: C0205 | C200: Client 0205 | D200: 45758 | E200: Online Reputation Management | F200: Online Reputation Management | G200: Hospitality | H200: Bengaluru | I200: New | J200: Delayed | K200: 6 | L200: 33 | M200: 41500 | N200: 2100 | O200: 39400 | P200: 20100 | Q200: 19300 | R200: 48.98 | S200: Email Campaign | T200: 1700 | U200: 3.4 | V200: Referral
A201: JSM11343 | B201: C0321 | C201: Client 0321 | D201: 45759 | E201: Online Reputation Management | F201: Online Reputation Management | G201: Education | H201: Mumbai | I201: New | J201: Completed | K201: 7 | L201: 52 | M201: 39600 | N201: 2000 | O201: 37600 | P201: 32500 | Q201: 5100 | R201: 13.56 | S201: Direct | T201: 2400 | U201: 3 | V201: Direct
A202: JSM10496 | B202: C0204 | C202: Client 0204 | D202: 45759 | E202: SEO | F202: SEO | G202: B2B Services | H202: Delhi Ncr | I202: New | J202: Completed | K202: 4 | L202: 69 | M202: 38000 | N202: 3800 | O202: 34200 | P202: 21300 | Q202: 12900 | R202: 37.72 | S202: Direct | T202: 4200 | U202: 4.4 | V202: Social
A203: JSM10162 | B203: C0164 | C203: Client 0164 | D203: 45759 | E203: SEO | F203: SEO | G203: Healthcare | H203: Hyderabad | I203: Returning | J203: Ongoing | K203: 7 | L203: 61 | M203: 98200 | N203: 9800 | O203: 88400 | P203: 72800 | Q203: 15600 | R203: 17.65 | S203: Direct | T203: 13300 | U203: 2.9 | V203: Paid Search
A204: JSM10716 | B204: C0372 | C204: Client 0372 | D204: 45759 | E204: SEO | F204: SEO | G204: Finance | H204: Bengaluru | I204: New | J204: Delayed | K204: 5 | L204: 60 | M204: 150400 | N204: 7500 | O204: 142900 | P204: 93900 | Q204: 49000 | R204: 34.29 | S204: Direct | T204: 11800 | U204: 4.1 | V204: Organic Search
A205: JSM11451 | B205: C0110 | C205: Client 0110 | D205: 45759 | E205: SEO | F205: SEO | G205: Finance | H205: Delhi Ncr | I205: Returning | J205: Delayed | K205: 9 | L205: 47 | M205: 59500 | N205: 0 | O205: 59500 | P205: 30800 | Q205: 28700 | R205: 48.24 | S205: Partner | T205: 7200 | U205: 3.7 | V205: Paid Search
A206: JSM10810 | B206: C0376 | C206: Client 0376 | D206: 45759 | E206: Mobile App Development | F206: Mobile App Development | G206: E-commerce | H206: Delhi Ncr | I206: New | J206: Ongoing | K206: 4 | L206: 58 | M206: 60200 | N206: 3000 | O206: 57200 | P206: 42600 | Q206: 14600 | R206: 25.52 | S206: Referral | T206: 5900 | U206: 2.7 | V206: Referral
A207: JSM10978 | B207: C0353 | C207: Client 0353 | D207: 45759 | E207: Web Development | F207: Web Development | G207: E-commerce | H207: Hyderabad | I207: New | J207: Completed | K207: 2 | L207: 70 | M207: 18100 | N207: 0 | O207: 18100 | P207: 13000 | Q207: 5100 | R207: 28.18 | S207: Referral | T207: 1200 | U207: 4.1 | V207: Paid Search
... A210: JSM10655 | B210: C0069 | C210: Client 0069 | D210: 45760 | E210: SEO | F210: SEO | G210: B2B Services | H210: Delhi Ncr | I210: Returning | J210: Ongoing | K210: 8 | L210: 19 | M210: 87200 | N210: 4400 | O210: 82800 | P210: 60200 | Q210: 22600 | R210: 27.29 | S210: Google | T210: 14100 | U210: 3.3 | V210: Organic Search
A211: JSM10306 | B211: C0045 | C211: Client 0045 | D211: 45760 | E211: Web Development | F211: Web Development | G211: Finance | H211: Ahmedabad | I211: Returning | J211: Ongoing | K211: 4 | L211: 16 | M211: 33200 | N211: 5000 | O211: 28200 | P211: 20800 | Q211: 7400 | R211: 26.24 | S211: Social Media | T211: 4200 | V211: Paid Search
A212: JSM11373 | B212: C0093 | C212: Client 0093 | D212: 45761 | E212: Content Marketing | F212: Content Marketing | G212: E-commerce | H212: Chennai | I212: Returning | J212: Completed | K212: 2 | L212: 66 | M212: 15200 | N212: 0 | O212: 15200 | P212: 10300 | Q212: 4900 | R212: 32.24 | S212: Google | T212: 2600 | U212: 4.4 | V212: Social
A213: JSM10346 | B213: C0301 | C213: Client 0301 | D213: 45761 | E213: Online Reputation Management | F213: Online Reputation Management | G213: E-commerce | H213: Ahmedabad | I213: New | J213: Completed | K213: 7 | L213: 22 | M213: 30900 | N213: 0 | O213: 30900 | P213: 23800 | Q213: 7100 | R213: 22.98 | S213: Partner | T213: 4100 | U213: 4.2 | V213: Referral
A214: JSM10491 | B214: C0298 | C214: Client 0298 | D214: 45761 | E214: Online Reputation Management | F214: Online Reputation Management | G214: E-commerce | H214: Hyderabad | I214: New | J214: Completed | K214: 7 | L214: 46 | M214: 59900 | N214: 9000 | O214: 50900 | P214: 32500 | Q214: 18400 | R214: 36.15 | S214: Referral | T214: 4400 | U214: 4.2 | V214: Social
A215: JSM10290 | B215: C0218 | C215: Client 0218 | D215: 45762 | E215: Web Development | F215: Web Development | G215: B2B Services | H215: Hyderabad | I215: New | J215: Completed | K215: 5 | L215: 37 | M215: 26000 | N215: 0 | O215: 26000 | P215: 18800 | Q215: 7200 | R215: 27.69 | S215: Social Media | T215: 2900 | U215: 2.9 | V215: Organic Search
A216: JSM10379 | B216: C0300 | C216: Client 0300 | D216: 45762 | E216: Online Reputation Management | F216: Online Reputation Management | G216: Finance | H216: Hyderabad | I216: New | J216: Completed | K216: 2 | L216: 34 | M216: 160100 | N216: 0 | O216: 160100 | P216: 93000 | Q216: 67100 | R216: 41.91 | S216: Social Media | T216: 22900 | U216: 3.4 | V216: Organic Search
A217: JSM10607 | B217: C0261 | C217: Client 0261 | D217: 45763 | E217: Web Design | F217: Web Design | G217: Finance | H217: Delhi Ncr | I217: New | J217: Ongoing | K217: 8 | L217: 5 | M217: 67400 | N217: 3400 | O217: 64000 | P217: 29400 | Q217: 34600 | R217: 54.06 | S217: Social Media | T217: 10000 | U217: 4.8 | V217: Direct
A218: JSM11036 | B218: C0179 | C218: Client 0179 | D218: 45764 | E218: Content Marketing | F218: Content Marketing | G218: Finance | H218: Hyderabad | I218: New | J218: Delayed | K218: 6 | L218: 35 | M218: 88000 | N218: 0 | O218: 88000 | P218: 50400 | Q218: 37600 | R218: 42.73 | S218: Partner | T218: 10600 | U218: 3.1 | V218: Organic Search
A219: JSM10984 | B219: C0194 | C219: Client 0194 | D219: 45765 | E219: Web Development | F219: Web Development | G219: B2B Services | H219: Delhi Ncr | I219: New | J219: Completed | K219: 3 | L219: 60 | M219: 66300 | N219: 3300 | O219: 63000 | P219: 53500 | Q219: 9500 | R219: 15.08 | S219: Email Campaign | T219: 3500 | U219: 4.4 | V219: Social
A220: JSM10014 | B220: C0260 | C220: Client 0260 | D220: 45766 | E220: Web Design | F220: Web Design | G220: E-commerce | H220: Chennai | I220: New | J220: Delayed | K220: 6 | L220: 62 | M220: 42600 | N220: 8500 | O220: 34100 | P220: 19900 | Q220: 14200 | R220: 41.64 | S220: Referral | T220: 5400 | U220: 4.8 | V220: Direct
A221: JSM10329 | B221: C0080 | C221: Client 0080 | D221: 45766 | E221: Social Media Marketing | F221: Social Media Marketing | G221: Manufacturing | H221: Delhi Ncr | I221: Returning | J221: Completed | K221: 4 | L221: 58 | M221: 97500 | N221: 19500 | O221: 78000 | P221: 47400 | Q221: 30600 | R221: 39.23 | S221: Email Campaign | T221: 13800 | U221: 3.5 | V221: Social
A222: JSM10792 | B222: C0345 | C222: Client 0345 | D222: 45766 | E222: Content Marketing | F222: Content Marketing | G222: Unknown | H222: Delhi Ncr | I222: New | J222: Completed | K222: 8 | L222: 34 | M222: 43800 | N222: 6600 | O222: 37200 | P222: 34400 | Q222: 2800 | R222: 7.53 | S222: Google | T222: 2300 | U222: 3.7 | V222: Paid Search
A223: JSM11150 | B223: C0333 | C223: Client 0333 | D223: 45767 | E223: Content Marketing | F223: Content Marketing | G223: B2B Services | H223: Chennai | I223: New | J223: Completed | K223: 7 | L223: 44 | M223: 82900 | N223: 8300 | O223: 74600 | P223: 35000 | Q223: 39600 | R223: 53.08 | S223: Google | T223: 4300 | U223: 4.1 | V223: Organic Search
... A289: JSM11375 | B289: C0014 | C289: Client 0014 | D289: 45798 | E289: PPC | F289: PPC | G289: Healthcare | H289: Kolkata | I289: Returning | J289: Completed | K289: 9 | L289: 5 | M289: 64200 | N289: 12800 | O289: 51400 | P289: 27200 | Q289: 24200 | R289: 47.08 | S289: Partner | T289: 7100 | U289: 3.7 | V289: Paid Search
A290: JSM10201 | B290: C0020 | C290: Client 0020 | D290: 45798 | E290: SEO | F290: SEO | G290: E-commerce | H290: Bengaluru | I290: Returning | J290: Ongoing | K290: 7 | M290: 60800 | N290: 0 | O290: 60800 | P290: 29600 | Q290: 31200 | R290: 51.32 | S290: Social Media | T290: 10500 | U290: 5 | V290: Direct
A291: JSM11141 | B291: C0129 | C291: Client 0129 | D291: 45799 | E291: SEO | F291: SEO | G291: Education | H291: Hyderabad | I291: Returning | J291: Delayed | K291: 7 | L291: 71 | M291: 61600 | N291: 0 | O291: 61600 | P291: 33900 | Q291: 27700 | R291: 44.97 | S291: Referral | T291: 10200 | U291: 4.1 | V291: Paid Search
A292: JSM10011 | B292: C0113 | C292: Client 0113 | D292: 45799 | E292: PPC | F292: PPC | G292: Education | H292: Bengaluru | I292: Returning | J292: Completed | K292: 10 | L292: 25 | M292: 62100 | N292: 3100 | O292: 59000 | P292: 26200 | Q292: 32800 | R292: 55.59 | S292: Partner | T292: 4000 | V292: Paid Search
A293: JSM11495 | B293: C0361 | C293: Client 0361 | D293: 45800 | E293: SEO | F293: SEO | G293: E-commerce | H293: Delhi Ncr | I293: New | J293: Delayed | K293: 5 | L293: 34 | M293: 64600 | N293: 0 | O293: 64600 | P293: 50400 | Q293: 14200 | R293: 21.98 | S293: Partner | T293: 11000 | U293: 3.7 | V293: Organic Search
A294: JSM11030 | B294: C0104 | C294: Client 0104 | D294: 45800 | E294: Social Media Marketing | F294: Social Media Marketing | G294: E-commerce | H294: Hyderabad | I294: Returning | J294: Ongoing | K294: 9 | L294: 53 | M294: 34800 | N294: 5200 | O294: 29600 | P294: 25700 | Q294: 3900 | R294: 13.18 | S294: Social Media | T294: 4300 | U294: 4.9 | V294: Referral
A295: JSM11282 | B295: C0244 | C295: Client 0244 | D295: 45801 | E295: Web Design | F295: Web Design | G295: Manufacturing | H295: Mumbai | I295: New | J295: Completed | K295: 9 | L295: 19 | M295: 33000 | N295: 1600 | O295: 31400 | P295: 14200 | Q295: 17200 | R295: 54.78 | S295: Social Media | T295: 2700 | U295: 3.7 | V295: Organic Search
A296: JSM10450 | B296: C0144 | C296: Client 0144 | D296: 45801 | E296: Social Media Marketing | F296: Social Media Marketing | G296: Education | H296: Mumbai | I296: Returning | J296: Completed | K296: 10 | L296: 42 | M296: 32400 | N296: 0 | O296: 32400 | P296: 17100 | Q296: 15300 | R296: 47.22 | S296: Email Campaign | T296: 3000 | U296: 4.6 | V296: Organic Search
A297: JSM10999 | B297: C0083 | C297: Client 0083 | D297: 45801 | E297: Mobile App Development | F297: Mobile App Development | G297: Finance | H297: Pune | I297: Returning | J297: Ongoing | K297: 7 | L297: 74 | M297: 63200 | N297: 0 | O297: 63200 | P297: 45600 | Q297: 17600 | R297: 27.85 | S297: Google | T297: 3600 | U297: 3.4 | V297: Paid Search
A298: JSM10257 | B298: C0197 | C298: Client 0197 | D298: 45801 | E298: PPC | F298: PPC | G298: Healthcare | H298: Delhi Ncr | I298: New | J298: Completed | K298: 3 | L298: 50 | M298: 75100 | N298: 0 | O298: 75100 | P298: 32600 | Q298: 42500 | R298: 56.59 | S298: Direct | T298: 5400 | U298: 3.3 | V298: Paid Search
A299: JSM10654 | B299: C0141 | C299: Client 0141 | D299: 45802 | E299: Social Media Marketing | F299: Social Media Marketing | G299: E-commerce | H299: Kolkata | I299: Returning | J299: Completed | K299: 8 | L299: 40 | M299: 77300 | N299: 3900 | O299: 73400 | P299: 42900 | Q299: 30500 | R299: 41.55 | S299: Referral | T299: 12300 | U299: 4.6 | V299: Direct
A300: JSM10844 | B300: C0401 | C300: Client 0401 | D300: 45803 | E300: Web Development | F300: Web Development | G300: Real Estate | H300: Ahmedabad | I300: New | J300: Completed | K300: 7 | L300: 21 | M300: 103100 | N300: 20600 | O300: 82500 | P300: 78700 | Q300: 3800 | R300: 4.61 | S300: Email Campaign | T300: 3400 | U300: 4.1 | V300: Referral
A301: JSM10132 | B301: C0036 | C301: Client 0036 | D301: 45803 | E301: Online Reputation Management | F301: Online Reputation Management | G301: Real Estate | H301: Ahmedabad | I301: Returning | J301: Completed | K301: 2 | L301: 25 | M301: 46300 | N301: 0 | O301: 46300 | P301: 37500 | Q301: 8800 | R301: 19.01 | S301: Direct | T301: 2800 | U301: 3.1 | V301: Referral
A302: JSM10082 | B302: C0137 | C302: Client 0137 | D302: 45803 | E302: Web Design | F302: Web Design | G302: Hospitality | H302: Kolkata | I302: Returning | J302: Completed | K302: 3 | L302: 41 | M302: 106700 | N302: 5300 | O302: 101400 | P302: 77100 | Q302: 24300 | R302: 23.96 | S302: Google | T302: 7600 | U302: 4.5 | V302: Referral
A303: JSM10940 | B303: C0417 | C303: Client 0417 | D303: 45804 | E303: PPC | F303: PPC | G303: Hospitality | H303: Mumbai | I303: New | J303: Ongoing | K303: 6 | L303: 53 | M303: 26500 | N303: 0 | O303: 26500 | P303: 20700 | Q303: 5800 | R303: 21.89 | S303: Referral | T303: 2100 | U303: 4.9 | V303: Referral
A304: JSM11027 | B304: C0036 | C304: Client 0036 | D304: 45804 | E304: Web Development | F304: Web Development | G304: Manufacturing | H304: Delhi Ncr | I304: Returning | J304: Completed | K304: 3 | L304: 27 | M304: 18800 | N304: 0 | O304: 18800 | P304: 14700 | Q304: 4100 | R304: 21.81 | S304: Partner | T304: 1300 | U304: 4 | V304: Direct
... A337: JSM11476 | B337: C0283 | C337: Client 0283 | D337: 45818 | E337: PPC | F337: PPC | G337: E-commerce | H337: Kolkata | I337: New | J337: Delayed | K337: 8 | L337: 48 | M337: 38200 | N337: 0 | O337: 38200 | P337: 22800 | Q337: 15400 | R337: 40.31 | S337: Google | T337: 5100 | U337: 4.8 | V337: Paid Search
A338: JSM11283 | B338: C0005 | C338: Client 0005 | D338: 45820 | E338: PPC | F338: PPC | G338: Education | H338: Bengaluru | I338: Returning | J338: Completed | K338: 8 | L338: 58 | M338: 51800 | N338: 0 | O338: 51800 | P338: 30900 | Q338: 20900 | R338: 40.35 | S338: Social Media | T338: 6900 | V338: Social
A339: JSM10372 | B339: C0264 | C339: Client 0264 | D339: 45820 | E339: SEO | F339: SEO | G339: E-commerce | H339: Mumbai | I339: New | J339: Completed | K339: 3 | L339: 61 | M339: 86900 | N339: 17400 | O339: 69500 | P339: 56700 | Q339: 12800 | R339: 18.42 | S339: Referral | T339: 7200 | U339: 4.2 | V339: Paid Search
A340: JSM11403 | B340: C0201 | C340: Client 0201 | D340: 45821 | E340: Web Development | F340: Web Development | G340: Real Estate | H340: Chennai | I340: New | J340: Completed | K340: 8 | L340: 55 | M340: 36300 | N340: 5400 | O340: 30900 | P340: 19100 | Q340: 11800 | R340: 38.19 | S340: Google | T340: 3100 | U340: 2.6 | V340: Paid Search
A341: JSM10660 | B341: C0091 | C341: Client 0091 | D341: 45821 | E341: Mobile App Development | F341: Mobile App Development | G341: Hospitality | H341: Pune | I341: Returning | J341: Completed | K341: 2 | L341: 27 | M341: 37700 | N341: 0 | O341: 37700 | P341: 18600 | Q341: 19100 | R341: 50.66 | S341: Direct | T341: 4700 | U341: 3.9 | V341: Social
A342: JSM10195 | B342: C0098 | C342: Client 0098 | D342: 45821 | E342: PPC | F342: PPC | G342: B2B Services | H342: Hyderabad | I342: Returning | J342: Cancelled | K342: 9 | L342: 24 | M342: 44000 | N342: 6600 | O342: 37400 | P342: 28700 | Q342: 8700 | R342: 23.26 | S342: Direct | T342: 4600 | U342: 4.3 | V342: Organic Search
A343: JSM11360 | B343: C0125 | C343: Client 0125 | D343: 45822 | E343: Social Media Marketing | F343: Social Media Marketing | G343: Healthcare | H343: Ahmedabad | I343: Returning | J343: Ongoing | K343: 7 | L343: 16 | M343: 36900 | N343: 5500 | O343: 31400 | P343: 17200 | Q343: 14200 | R343: 45.22 | S343: Partner | T343: 1800 | U343: 4.1 | V343: Referral
A344: JSM11057 | B344: C0149 | C344: Client 0149 | D344: 45823 | E344: SEO | F344: SEO | G344: Education | H344: Pune | I344: Returning | J344: Ongoing | K344: 4 | L344: 53 | M344: 44900 | N344: 0 | O344: 44900 | P344: 35100 | Q344: 9800 | R344: 21.83 | S344: Referral | T344: 4200 | U344: 4.3 | V344: Paid Search
A345: JSM10638 | B345: C0132 | C345: Client 0132 | D345: 45823 | E345: PPC | F345: PPC | G345: Manufacturing | H345: Ahmedabad | I345: Returning | J345: Completed | K345: 3 | L345: 43 | M345: 47700 | N345: 9500 | O345: 38200 | P345: 39000 | Q345: -800 | R345: -2.09 | S345: Social Media | T345: 4300 | U345: 4 | V345: Organic Search
A346: JSM10581 | B346: C0092 | C346: Client 0092 | D346: 45823 | E346: Online Reputation Management | F346: Online Reputation Management | G346: E-commerce | H346: Kolkata | I346: Returning | J346: Completed | K346: 6 | L346: 60 | M346: 30100 | N346: 0 | O346: 30100 | P346: 16200 | Q346: 13900 | R346: 46.18 | S346: Partner | T346: 3100 | U346: 4.2 | V346: Direct
A347: JSM10975 | B347: C0335 | C347: Client 0335 | D347: 45823 | E347: Web Development | F347: Web Development | G347: Education | H347: Delhi Ncr | I347: New | J347: Completed | K347: 3 | L347: 40 | M347: 51800 | N347: 7800 | O347: 44000 | P347: 33700 | Q347: 10300 | R347: 23.41 | S347: Email Campaign | T347: 2300 | U347: 4.8 | V347: Social
...

Sheet Cleaning_Log
A1: Column / Area | B1: Issue / Check | C1: Records affected | D1: Action taken
A2: All columns | B2: Exact duplicate records | C2: 11 | D2: Removed exact duplicate rows; first occurrence retained.
A3: Region | B3: Missing values | C3: 18 | D3: Replaced missing values with 'Unknown'.
A4: Industry | B4: Missing values | C4: 8 | D4: Replaced missing values with 'Unknown'.
A5: Lead_Source | B5: Missing values | C5: 12 | D5: Replaced missing values with 'Unknown'.
A6: Customer_Rating | B6: Missing values | C6: 15 | D6: Kept blank because the true value cannot safely be inferred.
A7: Project_Duration_Days | B7: Missing values | C7: 10 | D7: Kept blank because the true value cannot safely be inferred.
A8: Discount | B8: Missing values | C8: 10 | D8: Replaced missing values with 0 (treated as no discount).
A9: Service | B9: Inconsistent text/capitalization/spacing | C9: 1091 | D9: Standardized to one canonical format.
A10: Region | B10: Inconsistent text/capitalization/spacing | C10: 208 | D10: Standardized to one canonical format.
A11: Client_Type | B11: Inconsistent text/capitalization/spacing | C11: 15 | D11: Standardized to one canonical format.
A12: Project_Status | B12: Inconsistent text/capitalization/spacing | C12: 12 | D12: Standardized to one canonical format.
A13: Project_Date | B13: Date conversion | C13: 1501 | D13: Converted ISO and DD/MM/YYYY values to proper dates.
... A29: Profit_Margin_Pct | B29: Logical consistency | C29: 11 | D29: Recalculated as Profit / Revenue × 100.

Sheet Data_Dictionary
A1: Column | B1: Meaning
A2: Project_ID | B2: Unique project identifier
A3: Client_ID | B3: Unique client identifier
A4: Client_Name | B4: Client display name
A5: Project_Date | B5: Project start/date
A6: Service | B6: Service delivered
A7: Service_Category | B7: Service grouping
A8: Industry | B8: Client industry
A9: Region | B9: Client region
A10: Client_Type | B10: New or returning client
A11: Project_Status | B11: Project status
A12: Team_Size | B12: Number of team members
... A30: Marketing_ROI | B30: Marketing ROI

Sheet Beginner_Analysis
A1: BEGINNER BUSINESS ANALYSIS
A3: KPI | B3: Value
A4: Total Revenue | B4: =SUM(SalesData[Revenue]) -> 69877300
A5: Total Profit | B5: =SUM(SalesData[Profit]) -> 22734300
A6: Total Projects | B6: =COUNTA(SalesData[Project_ID]) -> 1501
A7: Total Clients | B7: =SUMPRODUCT(1/COUNTIF(SalesData[Client_ID],SalesData[Client_ID])) -> 405
A8: Average Project Value | B8: =AVERAGE(SalesData[Quoted_Value]) -> 50758.095
A9: Average Profit Margin | B9: =AVERAGE(SalesData[Profit_Margin_Pct]) -> 31.842978
A10: Average Customer Rating | B10: =AVERAGE(SalesData[Customer_Rating]) -> 4.0634459
A13: MONTHLY REVENUE ANALYSIS
A14: Month | B14: Revenue | C14: Profit | D14: Projects | E14: Avg Profit Margin
A15: 45658 | B15: =SUMIFS(SalesData[Revenue],SalesData[Project_Date],">="&A15,SalesData[Project_Date],"<"&EDATE(A15,1)) -> 2823200 | C15: =SUMIFS(SalesData[Profit],SalesData[Project_Date],">="&A15,SalesData[Project_Date],"<"&EDATE(A15,1)) -> 901400 | D15: =COUNTIFS(SalesData[Project_Date],">="&A15,SalesData[Project_Date],"<"&EDATE(A15,1)) -> 59 | E15: =IFERROR(AVERAGEIFS(SalesData[Profit_Margin_Pct],SalesData[Project_Date],">="&A15,SalesData[Project_Date],"<"&EDATE(A15,1)),0) -> 30.623898
A16: 45689 | B16: =SUMIFS(SalesData[Revenue],SalesData[Project_Date],">="&A16,SalesData[Project_Date],"<"&EDATE(A16,1)) -> 2622300 | C16: =SUMIFS(SalesData[Profit],SalesData[Project_Date],">="&A16,SalesData[Project_Date],"<"&EDATE(A16,1)) -> 847800 | D16: =COUNTIFS(SalesData[Project_Date],">="&A16,SalesData[Project_Date],"<"&EDATE(A16,1)) -> 56 | E16: =IFERROR(AVERAGEIFS(SalesData[Profit_Margin_Pct],SalesData[Project_Date],">="&A16,SalesData[Project_Date],"<"&EDATE(A16,1)),0) -> 31.15125
A17: 45717 | B17: =SUMIFS(SalesData[Revenue],SalesData[Project_Date],">="&A17,SalesData[Project_Date],"<"&EDATE(A17,1)) -> 2921200 | C17: =SUMIFS(SalesData[Profit],SalesData[Project_Date],">="&A17,SalesData[Project_Date],"<"&EDATE(A17,1)) -> 957800 | D17: =COUNTIFS(SalesData[Project_Date],">="&A17,SalesData[Project_Date],"<"&EDATE(A17,1)) -> 60 | E17: =IFERROR(AVERAGEIFS(SalesData[Profit_Margin_Pct],SalesData[Project_Date],">="&A17,SalesData[Project_Date],"<"&EDATE(A17,1)),0) -> 32.729667
A18: 45748 | B18: =SUMIFS(SalesData[Revenue],SalesData[Project_Date],">="&A18,SalesData[Project_Date],"<"&EDATE(A18,1)) -> 3502500 | C18: =SUMIFS(SalesData[Profit],SalesData[Project_Date],">="&A18,SalesData[Project_Date],"<"&EDATE(A18,1)) -> 1139800 | D18: =COUNTIFS(SalesData[Project_Date],">="&A18,SalesData[Project_Date],"<"&EDATE(A18,1)) -> 67 | E18: =IFERROR(AVERAGEIFS(SalesData[Profit_Margin_Pct],SalesData[Project_Date],">="&A18,SalesData[Project_Date],"<"&EDATE(A18,1)),0) -> 32.155224
A19: 45778 | B19: =SUMIFS(SalesData[Revenue],SalesData[Project_Date],">="&A19,SalesData[Project_Date],"<"&EDATE(A19,1)) -> 3582200 | C19: =SUMIFS(SalesData[Profit],SalesData[Project_Date],">="&A19,SalesData[Project_Date],"<"&EDATE(A19,1)) -> 1056200 | D19: =COUNTIFS(SalesData[Project_Date],">="&A19,SalesData[Project_Date],"<"&EDATE(A19,1)) -> 78 | E19: =IFERROR(AVERAGEIFS(SalesData[Profit_Margin_Pct],SalesData[Project_Date],">="&A19,SalesData[Project_Date],"<"&EDATE(A19,1)),0) -> 29.956667
A20: 45809 | B20: =SUMIFS(SalesData[Revenue],SalesData[Project_Date],">="&A20,SalesData[Project_Date],"<"&EDATE(A20,1)) -> 2628000 | C20: =SUMIFS(SalesData[Profit],SalesData[Project_Date],">="&A20,SalesData[Project_Date],"<"&EDATE(A20,1)) -> 851300 | D20: =COUNTIFS(SalesData[Project_Date],">="&A20,SalesData[Project_Date],"<"&EDATE(A20,1)) -> 60 | E20: =IFERROR(AVERAGEIFS(SalesData[Profit_Margin_Pct],SalesData[Project_Date],">="&A20,SalesData[Project_Date],"<"&EDATE(A20,1)),0) -> 30.615
A21: 45839 | B21: =SUMIFS(SalesData[Revenue],SalesData[Project_Date],">="&A21,SalesData[Project_Date],"<"&EDATE(A21,1)) -> 2943200 | C21: =SUMIFS(SalesData[Profit],SalesData[Project_Date],">="&A21,SalesData[Project_Date],"<"&EDATE(A21,1)) -> 944600 | D21: =COUNTIFS(SalesData[Project_Date],">="&A21,SalesData[Project_Date],"<"&EDATE(A21,1)) -> 64 | E21: =IFERROR(AVERAGEIFS(SalesData[Profit_Margin_Pct],SalesData[Project_Date],">="&A21,SalesData[Project_Date],"<"&EDATE(A21,1)),0) -> 32.019531
A22: 45870 | B22: =SUMIFS(SalesData[Revenue],SalesData[Project_Date],">="&A22,SalesData[Project_Date],"<"&EDATE(A22,1)) -> 2273800 | C22: =SUMIFS(SalesData[Profit],SalesData[Project_Date],">="&A22,SalesData[Project_Date],"<"&EDATE(A22,1)) -> 760600 | D22: =COUNTIFS(SalesData[Project_Date],">="&A22,SalesData[Project_Date],"<"&EDATE(A22,1)) -> 50 | E22: =IFERROR(AVERAGEIFS(SalesData[Profit_Margin_Pct],SalesData[Project_Date],">="&A22,SalesData[Project_Date],"<"&EDATE(A22,1)),0) -> 32.2208
A23: 45901 | B23: =SUMIFS(SalesData[Revenue],SalesData[Project_Date],">="&A23,SalesData[Project_Date],"<"&EDATE(A23,1)) -> 2213300 | C23: =SUMIFS(SalesData[Profit],SalesData[Project_Date],">="&A23,SalesData[Project_Date],"<"&EDATE(A23,1)) -> 698200 | D23: =COUNTIFS(SalesData[Project_Date],">="&A23,SalesData[Project_Date],"<"&EDATE(A23,1)) -> 45 | E23: =IFERROR(AVERAGEIFS(SalesData[Profit_Margin_Pct],SalesData[Project_Date],">="&A23,SalesData[Project_Date],"<"&EDATE(A23,1)),0) -> 31.446
A24: 45931 | B24: =SUMIFS(SalesData[Revenue],SalesData[Project_Date],">="&A24,SalesData[Project_Date],"<"&EDATE(A24,1)) -> 3120200 | C24: =SUMIFS(SalesData[Profit],SalesData[Project_Date],">="&A24,SalesData[Project_Date],"<"&EDATE(A24,1)) -> 914300 | D24: =COUNTIFS(SalesData[Project_Date],">="&A24,SalesData[Project_Date],"<"&EDATE(A24,1)) -> 66 | E24: =IFERROR(AVERAGEIFS(SalesData[Profit_Margin_Pct],SalesData[Project_Date],">="&A24,SalesData[Project_Date],"<"&EDATE(A24,1)),0) -> 30.087121
A25: 45962 | B25: =SUMIFS(SalesData[Revenue],SalesData[Project_Date],">="&A25,SalesData[Project_Date],"<"&EDATE(A25,1)) -> 3214200 | C25: =SUMIFS(SalesData[Profit],SalesData[Project_Date],">="&A25,SalesData[Project_Date],"<"&EDATE(A25,1)) -> 1116100 | D25: =COUNTIFS(SalesData[Project_Date],">="&A25,SalesData[Project_Date],"<"&EDATE(A25,1)) -> 69 | E25: =IFERROR(AVERAGEIFS(SalesData[Profit_Margin_Pct],SalesData[Project_Date],">="&A25,SalesData[Project_Date],"<"&EDATE(A25,1)),0) -> 33.118116
A26: 45992 | B26: =SUMIFS(SalesData[Revenue],SalesData[Project_Date],">="&A26,SalesData[Project_Date],"<"&EDATE(A26,1)) -> 2786200 | C26: =SUMIFS(SalesData[Profit],SalesData[Project_Date],">="&A26,SalesData[Project_Date],"<"&EDATE(A26,1)) -> 917200 | D26: =COUNTIFS(SalesData[Project_Date],">="&A26,SalesData[Project_Date],"<"&EDATE(A26,1)) -> 69 | E26: =IFERROR(AVERAGEIFS(SalesData[Profit_Margin_Pct],SalesData[Project_Date],">="&A26,SalesData[Project_Date],"<"&EDATE(A26,1)),0) -> 33.065362
... A38: 46357 | B38: =SUMIFS(SalesData[Revenue],SalesData[Project_Date],">="&A38,SalesData[Project_Date],"<"&EDATE(A38,1)) -> 3717700 | C38: =SUMIFS(SalesData[Profit],SalesData[Project_Date],">="&A38,SalesData[Project_Date],"<"&EDATE(A38,1)) -> 1151500 | D38: =COUNTIFS(SalesData[Project_Date],">="&A38,SalesData[Project_Date],"<"&EDATE(A38,1)) -> 77 | E38: =IFERROR(AVERAGEIFS(SalesData[Profit_Margin_Pct],SalesData[Project_Date],">="&A38,SalesData[Project_Date],"<"&EDATE(A38,1)),0) -> 30.094675
A40: SERVICE PERFORMANCE
A41: Service | B41: Revenue | C41: Profit | D41: Projects | E41: Avg Margin | F41: Revenue Share
A42: SEO | B42: =SUMIF(SalesData[Service],A42,SalesData[Revenue]) -> 8439000 | C42: =SUMIF(SalesData[Service],A42,SalesData[Profit]) -> 2754600 | D42: =COUNTIF(SalesData[Service],A42) -> 170 | E42: =IFERROR(AVERAGEIF(SalesData[Service],A42,SalesData[Profit_Margin_Pct]),0) -> 32.063 | F42: =IFERROR(B42/$B$4,0) -> 0.12076883
A43: Social Media Marketing | B43: =SUMIF(SalesData[Service],A43,SalesData[Revenue]) -> 8645500 | C43: =SUMIF(SalesData[Service],A43,SalesData[Profit]) -> 2735400 | D43: =COUNTIF(SalesData[Service],A43) -> 188 | E43: =IFERROR(AVERAGEIF(SalesData[Service],A43,SalesData[Profit_Margin_Pct]),0) -> 31.681755 | F43: =IFERROR(B43/$B$4,0) -> 0.12372401
A44: Web Design | B44: =SUMIF(SalesData[Service],A44,SalesData[Revenue]) -> 8576500 | C44: =SUMIF(SalesData[Service],A44,SalesData[Profit]) -> 2898700 | D44: =COUNTIF(SalesData[Service],A44) -> 174 | E44: =IFERROR(AVERAGEIF(SalesData[Service],A44,SalesData[Profit_Margin_Pct]),0) -> 32.972759 | F44: =IFERROR(B44/$B$4,0) -> 0.12273657
A45: Web Development | B45: =SUMIF(SalesData[Service],A45,SalesData[Revenue]) -> 9287200 | C45: =SUMIF(SalesData[Service],A45,SalesData[Profit]) -> 3033500 | D45: =COUNTIF(SalesData[Service],A45) -> 202 | E45: =IFERROR(AVERAGEIF(SalesData[Service],A45,SalesData[Profit_Margin_Pct]),0) -> 32.251584 | F45: =IFERROR(B45/$B$4,0) -> 0.13290725
A46: Content Marketing | B46: =SUMIF(SalesData[Service],A46,SalesData[Revenue]) -> 8179100 | C46: =SUMIF(SalesData[Service],A46,SalesData[Profit]) -> 2639800 | D46: =COUNTIF(SalesData[Service],A46) -> 186 | E46: =IFERROR(AVERAGEIF(SalesData[Service],A46,SalesData[Profit_Margin_Pct]),0) -> 31.601129 | F46: =IFERROR(B46/$B$4,0) -> 0.11704946
A47: PPC | B47: =SUMIF(SalesData[Service],A47,SalesData[Revenue]) -> 8826000 | C47: =SUMIF(SalesData[Service],A47,SalesData[Profit]) -> 2830200 | D47: =COUNTIF(SalesData[Service],A47) -> 188 | E47: =IFERROR(AVERAGEIF(SalesData[Service],A47,SalesData[Profit_Margin_Pct]),0) -> 31.170053 | F47: =IFERROR(B47/$B$4,0) -> 0.12630711
A48: Online Reputation Management | B48: =SUMIF(SalesData[Service],A48,SalesData[Revenue]) -> 8592300 | C48: =SUMIF(SalesData[Service],A48,SalesData[Profit]) -> 2910100 | D48: =COUNTIF(SalesData[Service],A48) -> 184 | E48: =IFERROR(AVERAGEIF(SalesData[Service],A48,SalesData[Profit_Margin_Pct]),0) -> 33.065109 | F48: =IFERROR(B48/$B$4,0) -> 0.12296268
A49: Mobile App Development | B49: =SUMIF(SalesData[Service],A49,SalesData[Revenue]) -> 9331700 | C49: =SUMIF(SalesData[Service],A49,SalesData[Profit]) -> 2932000 | D49: =COUNTIF(SalesData[Service],A49) -> 209 | E49: =IFERROR(AVERAGEIF(SalesData[Service],A49,SalesData[Profit_Margin_Pct]),0) -> 30.218134 | F49: =IFERROR(B49/$B$4,0) -> 0.13354408
A52: REGIONAL PERFORMANCE
A53: Region | B53: Revenue | C53: Profit | D53: Projects | E53: Avg Margin
A54: Mumbai | B54: =SUMIF(SalesData[Region],A54,SalesData[Revenue]) -> 7313200 | C54: =SUMIF(SalesData[Region],A54,SalesData[Profit]) -> 2329000 | D54: =COUNTIF(SalesData[Region],A54) -> 158 | E54: =IFERROR(AVERAGEIF(SalesData[Region],A54,SalesData[Profit_Margin_Pct]),0) -> 31.62538
A55: Delhi Ncr | B55: =SUMIF(SalesData[Region],A55,SalesData[Revenue]) -> 8293700 | C55: =SUMIF(SalesData[Region],A55,SalesData[Profit]) -> 2646400 | D55: =COUNTIF(SalesData[Region],A55) -> 194 | E55: =IFERROR(AVERAGEIF(SalesData[Region],A55,SalesData[Profit_Margin_Pct]),0) -> 31.055773
A56: Bengaluru | B56: =SUMIF(SalesData[Region],A56,SalesData[Revenue]) -> 10792000 | C56: =SUMIF(SalesData[Region],A56,SalesData[Profit]) -> 3605300 | D56: =COUNTIF(SalesData[Region],A56) -> 212 | E56: =IFERROR(AVERAGEIF(SalesData[Region],A56,SalesData[Profit_Margin_Pct]),0) -> 32.613538
A57: Pune | B57: =SUMIF(SalesData[Region],A57,SalesData[Revenue]) -> 8568000 | C57: =SUMIF(SalesData[Region],A57,SalesData[Profit]) -> 2745200 | D57: =COUNTIF(SalesData[Region],A57) -> 180 | E57: =IFERROR(AVERAGEIF(SalesData[Region],A57,SalesData[Profit_Margin_Pct]),0) -> 31.332167
A58: Hyderabad | B58: =SUMIF(SalesData[Region],A58,SalesData[Revenue]) -> 8958900 | C58: =SUMIF(SalesData[Region],A58,SalesData[Profit]) -> 2991200 | D58: =COUNTIF(SalesData[Region],A58) -> 180 | E58: =IFERROR(AVERAGEIF(SalesData[Region],A58,SalesData[Profit_Margin_Pct]),0) -> 32.479556
A59: Chennai | B59: =SUMIF(SalesData[Region],A59,SalesData[Revenue]) -> 8515900 | C59: =SUMIF(SalesData[Region],A59,SalesData[Profit]) -> 2889000 | D59: =COUNTIF(SalesData[Region],A59) -> 186 | E59: =IFERROR(AVERAGEIF(SalesData[Region],A59,SalesData[Profit_Margin_Pct]),0) -> 33.119839
A60: Ahmedabad | B60: =SUMIF(SalesData[Region],A60,SalesData[Revenue]) -> 8194700 | C60: =SUMIF(SalesData[Region],A60,SalesData[Profit]) -> 2474200 | D60: =COUNTIF(SalesData[Region],A60) -> 190 | E60: =IFERROR(AVERAGEIF(SalesData[Region],A60,SalesData[Profit_Margin_Pct]),0) -> 29.765053
A61: Kolkata | B61: =SUMIF(SalesData[Region],A61,SalesData[Revenue]) -> 8336200 | C61: =SUMIF(SalesData[Region],A61,SalesData[Profit]) -> 2701300 | D61: =COUNTIF(SalesData[Region],A61) -> 183 | E61: =IFERROR(AVERAGEIF(SalesData[Region],A61,SalesData[Profit_Margin_Pct]),0) -> 32.334699
A62: Unknown | B62: =SUMIF(SalesData[Region],A62,SalesData[Revenue]) -> 904700 | C62: =SUMIF(SalesData[Region],A62,SalesData[Profit]) -> 352700 | D62: =COUNTIF(SalesData[Region],A62) -> 18 | E62: =IFERROR(AVERAGEIF(SalesData[Region],A62,SalesData[Profit_Margin_Pct]),0) -> 35.644444
A64: CLIENT TYPE
A65: Client Type | B65: Revenue | C65: Profit | D65: Projects
A66: New | B66: =SUMIF(SalesData[Client_Type],A66,SalesData[Revenue]) -> 43076600 | C66: =SUMIF(SalesData[Client_Type],A66,SalesData[Profit]) -> 13795100 | D66: =COUNTIF(SalesData[Client_Type],A66) -> 929
A67: Returning | B67: =SUMIF(SalesData[Client_Type],A67,SalesData[Revenue]) -> 26800700 | C67: =SUMIF(SalesData[Client_Type],A67,SalesData[Profit]) -> 8939200 | D67: =COUNTIF(SalesData[Client_Type],A67) -> 572
A69: LEAD SOURCE
A70: Lead Source | B70: Revenue | C70: Profit | D70: Projects | E70: Marketing Spend | F70: ROI
A71: Direct | B71: =SUMIF(SalesData[Lead_Source],A71,SalesData[Revenue]) -> 13274500 | C71: =SUMIF(SalesData[Lead_Source],A71,SalesData[Profit]) -> 4361600 | D71: =COUNTIF(SalesData[Lead_Source],A71) -> 268 | E71: =SUMIF(SalesData[Lead_Source],A71,SalesData[Marketing_Spend]) -> 1428400 | F71: =IFERROR((B71-E71)/E71,0) -> 8.2932652
A72: Email Campaign | B72: =SUMIF(SalesData[Lead_Source],A72,SalesData[Revenue]) -> 10926800 | C72: =SUMIF(SalesData[Lead_Source],A72,SalesData[Profit]) -> 3566100 | D72: =COUNTIF(SalesData[Lead_Source],A72) -> 246 | E72: =SUMIF(SalesData[Lead_Source],A72,SalesData[Marketing_Spend]) -> 1151100 | F72: =IFERROR((B72-E72)/E72,0) -> 8.4924854
A73: Google | B73: =SUMIF(SalesData[Lead_Source],A73,SalesData[Revenue]) -> 11135800 | C73: =SUMIF(SalesData[Lead_Source],A73,SalesData[Profit]) -> 3613100 | D73: =COUNTIF(SalesData[Lead_Source],A73) -> 232 | E73: =SUMIF(SalesData[Lead_Source],A73,SalesData[Marketing_Spend]) -> 1206300 | F73: =IFERROR((B73-E73)/E73,0) -> 8.2313686
A74: Partner | B74: =SUMIF(SalesData[Lead_Source],A74,SalesData[Revenue]) -> 11973600 | C74: =SUMIF(SalesData[Lead_Source],A74,SalesData[Profit]) -> 3837800 | D74: =COUNTIF(SalesData[Lead_Source],A74) -> 262 | E74: =SUMIF(SalesData[Lead_Source],A74,SalesData[Marketing_Spend]) -> 1352800 | F74: =IFERROR((B74-E74)/E74,0) -> 7.8509758
A75: Referral | B75: =SUMIF(SalesData[Lead_Source],A75,SalesData[Revenue]) -> 10488100 | C75: =SUMIF(SalesData[Lead_Source],A75,SalesData[Profit]) -> 3312400 | D75: =COUNTIF(SalesData[Lead_Source],A75) -> 233 | E75: =SUMIF(SalesData[Lead_Source],A75,SalesData[Marketing_Spend]) -> 1170800 | F75: =IFERROR((B75-E75)/E75,0) -> 7.9580629
A76: Social Media | B76: =SUMIF(SalesData[Lead_Source],A76,SalesData[Revenue]) -> 11726200 | C76: =SUMIF(SalesData[Lead_Source],A76,SalesData[Profit]) -> 3951200 | D76: =COUNTIF(SalesData[Lead_Source],A76) -> 248 | E76: =SUMIF(SalesData[Lead_Source],A76,SalesData[Marketing_Spend]) -> 1319900 | F76: =IFERROR((B76-E76)/E76,0) -> 7.8841579
A77: Unknown | B77: =SUMIF(SalesData[Lead_Source],A77,SalesData[Revenue]) -> 352300 | C77: =SUMIF(SalesData[Lead_Source],A77,SalesData[Profit]) -> 92100 | D77: =COUNTIF(SalesData[Lead_Source],A77) -> 12 | E77: =SUMIF(SalesData[Lead_Source],A77,SalesData[Marketing_Spend]) -> 31000 | F77: =IFERROR((B77-E77)/E77,0) -> 10.364516
A79: TOP 5 CLIENTS
A80: Rank | B80: Client ID | C80: Client Name | D80: Projects | E80: Revenue | F80: Profit | G80: Avg Rating
A81: 1 | B81: C0050 | C81: =INDEX(SalesData[Client_Name],MATCH(B81,SalesData[Client_ID],0)) -> Client 0050 | D81: =COUNTIF(SalesData[Client_ID],B81) -> 9 | E81: =SUMIF(SalesData[Client_ID],B81,SalesData[Revenue]) -> 528400 | F81: =SUMIF(SalesData[Client_ID],B81,SalesData[Profit]) -> 166900 | G81: =IFERROR(AVERAGEIF(SalesData[Client_ID],B81,SalesData[Customer_Rating]),0) -> 4.5888889
A82: 2 | B82: C0344 | C82: =INDEX(SalesData[Client_Name],MATCH(B82,SalesData[Client_ID],0)) -> Client 0344 | D82: =COUNTIF(SalesData[Client_ID],B82) -> 9 | E82: =SUMIF(SalesData[Client_ID],B82,SalesData[Revenue]) -> 509600 | F82: =SUMIF(SalesData[Client_ID],B82,SalesData[Profit]) -> 178900 | G82: =IFERROR(AVERAGEIF(SalesData[Client_ID],B82,SalesData[Customer_Rating]),0) -> 3.9333333
A83: 3 | B83: C0086 | C83: =INDEX(SalesData[Client_Name],MATCH(B83,SalesData[Client_ID],0)) -> Client 0086 | D83: =COUNTIF(SalesData[Client_ID],B83) -> 9 | E83: =SUMIF(SalesData[Client_ID],B83,SalesData[Revenue]) -> 445000 | F83: =SUMIF(SalesData[Client_ID],B83,SalesData[Profit]) -> 120100 | G83: =IFERROR(AVERAGEIF(SalesData[Client_ID],B83,SalesData[Customer_Rating]),0) -> 3.7555556
A84: 4 | B84: C0241 | C84: =INDEX(SalesData[Client_Name],MATCH(B84,SalesData[Client_ID],0)) -> Client 0241 | D84: =COUNTIF(SalesData[Client_ID],B84) -> 8 | E84: =SUMIF(SalesData[Client_ID],B84,SalesData[Revenue]) -> 440400 | F84: =SUMIF(SalesData[Client_ID],B84,SalesData[Profit]) -> 107700 | G84: =IFERROR(AVERAGEIF(SalesData[Client_ID],B84,SalesData[Customer_Rating]),0) -> 3.975
A85: 5 | B85: C0047 | C85: =INDEX(SalesData[Client_Name],MATCH(B85,SalesData[Client_ID],0)) -> Client 0047 | D85: =COUNTIF(SalesData[Client_ID],B85) -> 8 | E85: =SUMIF(SalesData[Client_ID],B85,SalesData[Revenue]) -> 432300 | F85: =SUMIF(SalesData[Client_ID],B85,SalesData[Profit]) -> 118800 | G85: =IFERROR(AVERAGEIF(SalesData[Client_ID],B85,SalesData[Customer_Rating]),0) -> 3.9125
A90: BEGINNER BUSINESS OBSERVATIONS
A92: 2. Total revenue is ₹69,877,300 across 1,501 projects, with total profit of ₹22,734,300.
A93: 3. Mobile App Development is the highest-revenue service, generating ₹9,331,700.
A94: 4. Web Development generates the highest total profit at ₹3,033,500.
A95: 5. Bengaluru is the highest-revenue region, contributing ₹10,792,000 from 212 projects.
A96: 6. Returning clients account for 38.4% of total revenue.
A97: 7. Direct is the largest lead source by revenue, generating ₹13,274,500.
A98: 8. There are 405 unique clients; 358 have more than one project, giving a repeat-client rate of 88.4%.

Sheet Beginner_Dashboard
A1: DASHBOARD
A2: Business Performance Dashboard – Beginner Level
A4: Total Revenue | D4: Total Profit | G4: Projects | J4: Clients
A5: =Beginner_Analysis!B4 -> 69877300 | D5: =Beginner_Analysis!B5 -> 22734300 | G5: =Beginner_Analysis!B6 -> 1501 | J5: =Beginner_Analysis!B7 -> 405
A7: Avg Project Value | D7: Avg Margin | G7: Avg Rating
A8: =Beginner_Analysis!B8 -> 50758.095 | D8: =Beginner_Analysis!B9 -> 31.842978 | G8: =Beginner_Analysis!B10 -> 4.0634459
A11: Month | B11: Revenue | C11: Profit | F11: Service | G11: Revenue | H11: Profit
A12: =Beginner_Analysis!A15 -> 45658 | B12: =Beginner_Analysis!B15 -> 2823200 | C12: =Beginner_Analysis!C15 -> 901400 | F12: =Beginner_Analysis!A42 -> SEO | G12: =Beginner_Analysis!B42 -> 8439000 | H12: =Beginner_Analysis!C42 -> 2754600
A13: =Beginner_Analysis!A16 -> 45689 | B13: =Beginner_Analysis!B16 -> 2622300 | C13: =Beginner_Analysis!C16 -> 847800 | F13: =Beginner_Analysis!A43 -> Social Media Marketing | G13: =Beginner_Analysis!B43 -> 8645500 | H13: =Beginner_Analysis!C43 -> 2735400
A14: =Beginner_Analysis!A17 -> 45717 | B14: =Beginner_Analysis!B17 -> 2921200 | C14: =Beginner_Analysis!C17 -> 957800 | F14: =Beginner_Analysis!A44 -> Web Design | G14: =Beginner_Analysis!B44 -> 8576500 | H14: =Beginner_Analysis!C44 -> 2898700
A15: =Beginner_Analysis!A18 -> 45748 | B15: =Beginner_Analysis!B18 -> 3502500 | C15: =Beginner_Analysis!C18 -> 1139800 | F15: =Beginner_Analysis!A45 -> Web Development | G15: =Beginner_Analysis!B45 -> 9287200 | H15: =Beginner_Analysis!C45 -> 3033500
A16: =Beginner_Analysis!A19 -> 45778 | B16: =Beginner_Analysis!B19 -> 3582200 | C16: =Beginner_Analysis!C19 -> 1056200 | F16: =Beginner_Analysis!A46 -> Content Marketing | G16: =Beginner_Analysis!B46 -> 8179100 | H16: =Beginner_Analysis!C46 -> 2639800
A17: =Beginner_Analysis!A20 -> 45809 | B17: =Beginner_Analysis!B20 -> 2628000 | C17: =Beginner_Analysis!C20 -> 851300 | F17: =Beginner_Analysis!A47 -> PPC | G17: =Beginner_Analysis!B47 -> 8826000 | H17: =Beginner_Analysis!C47 -> 2830200
A18: =Beginner_Analysis!A21 -> 45839 | B18: =Beginner_Analysis!B21 -> 2943200 | C18: =Beginner_Analysis!C21 -> 944600 | F18: =Beginner_Analysis!A48 -> Online Reputation Management | G18: =Beginner_Analysis!B48 -> 8592300 | H18: =Beginner_Analysis!C48 -> 2910100
A19: =Beginner_Analysis!A22 -> 45870 | B19: =Beginner_Analysis!B22 -> 2273800 | C19: =Beginner_Analysis!C22 -> 760600 | F19: =Beginner_Analysis!A49 -> Mobile App Development | G19: =Beginner_Analysis!B49 -> 9331700 | H19: =Beginner_Analysis!C49 -> 2932000
A20: =Beginner_Analysis!A23 -> 45901 | B20: =Beginner_Analysis!B23 -> 2213300 | C20: =Beginner_Analysis!C23 -> 698200
A21: =Beginner_Analysis!A24 -> 45931 | B21: =Beginner_Analysis!B24 -> 3120200 | C21: =Beginner_Analysis!C24 -> 914300
A22: =Beginner_Analysis!A25 -> 45962 | B22: =Beginner_Analysis!B25 -> 3214200 | C22: =Beginner_Analysis!C25 -> 1116100
A23: =Beginner_Analysis!A26 -> 45992 | B23: =Beginner_Analysis!B26 -> 2786200 | C23: =Beginner_Analysis!C26 -> 917200
A24: =Beginner_Analysis!A27 -> 46023 | B24: =Beginner_Analysis!B27 -> 2483900 | C24: =Beginner_Analysis!C27 -> 854600
A25: =Beginner_Analysis!A28 -> 46054 | B25: =Beginner_Analysis!B28 -> 3022400 | C25: =Beginner_Analysis!C28 -> 942000
A26: =Beginner_Analysis!A29 -> 46082 | B26: =Beginner_Analysis!B29 -> 2271300 | C26: =Beginner_Analysis!C29 -> 753900
A27: =Beginner_Analysis!A30 -> 46113 | B27: =Beginner_Analysis!B30 -> 3050000 | C27: =Beginner_Analysis!C30 -> 1094200
A28: =Beginner_Analysis!A31 -> 46143 | B28: =Beginner_Analysis!B31 -> 2620300 | C28: =Beginner_Analysis!C31 -> 905600
A29: =Beginner_Analysis!A32 -> 46174 | B29: =Beginner_Analysis!B32 -> 2657700 | C29: =Beginner_Analysis!C32 -> 766400
A30: =Beginner_Analysis!A33 -> 46204 | B30: =Beginner_Analysis!B33 -> 3359200 | C30: =Beginner_Analysis!C33 -> 1061300
A31: =Beginner_Analysis!A34 -> 46235 | B31: =Beginner_Analysis!B34 -> 3319500 | C31: =Beginner_Analysis!C34 -> 1076900
... A35: =Beginner_Analysis!A38 -> 46357 | B35: =Beginner_Analysis!B38 -> 3717700 | C35: =Beginner_Analysis!C38 -> 1151500

Sheet Intermediate_Analysis
A1: INTERMEDIATE – CUSTOMER, REVENUE & BUSINESS ANALYSIS
A3: Metric | B3: Value
A4: Unique Clients | B4: =SUMPRODUCT(1/COUNTIF(SalesData[Client_ID],SalesData[Client_ID])) -> 405
A5: Repeat Clients | B5: =SUMPRODUCT((COUNTIF(SalesData[Client_ID],SalesData[Client_ID])>1)/COUNTIF(SalesData[Client_ID],SalesData[Client_ID])) -> 358
A6: Repeat Client % | B6: =IFERROR(B5/B4,0) -> 0.88395062
A7: New Client Revenue | B7: =SUMIF(SalesData[Client_Type],"New",SalesData[Revenue]) -> 43076600
A8: Returning Client Revenue | B8: =SUMIF(SalesData[Client_Type],"Returning",SalesData[Revenue]) -> 26800700
A9: Average Revenue per Client | B9: =IFERROR(SUM(SalesData[Revenue])/B4,0) -> 172536.54
A13: SERVICE PROFITABILITY
A14: Service | B14: Revenue | C14: Profit | D14: Projects | E14: Avg Margin | F14: Revenue Share
A15: SEO | B15: =SUMIF(SalesData[Service],A15,SalesData[Revenue]) -> 8439000 | C15: =SUMIF(SalesData[Service],A15,SalesData[Profit]) -> 2754600 | D15: =COUNTIF(SalesData[Service],A15) -> 170 | E15: =IFERROR(AVERAGEIF(SalesData[Service],A15,SalesData[Profit_Margin_Pct]),0) -> 32.063 | F15: =IFERROR(B15/SUM(SalesData[Revenue]),0) -> 0.12076883
A16: Social Media Marketing | B16: =SUMIF(SalesData[Service],A16,SalesData[Revenue]) -> 8645500 | C16: =SUMIF(SalesData[Service],A16,SalesData[Profit]) -> 2735400 | D16: =COUNTIF(SalesData[Service],A16) -> 188 | E16: =IFERROR(AVERAGEIF(SalesData[Service],A16,SalesData[Profit_Margin_Pct]),0) -> 31.681755 | F16: =IFERROR(B16/SUM(SalesData[Revenue]),0) -> 0.12372401
A17: Web Design | B17: =SUMIF(SalesData[Service],A17,SalesData[Revenue]) -> 8576500 | C17: =SUMIF(SalesData[Service],A17,SalesData[Profit]) -> 2898700 | D17: =COUNTIF(SalesData[Service],A17) -> 174 | E17: =IFERROR(AVERAGEIF(SalesData[Service],A17,SalesData[Profit_Margin_Pct]),0) -> 32.972759 | F17: =IFERROR(B17/SUM(SalesData[Revenue]),0) -> 0.12273657
A18: Web Development | B18: =SUMIF(SalesData[Service],A18,SalesData[Revenue]) -> 9287200 | C18: =SUMIF(SalesData[Service],A18,SalesData[Profit]) -> 3033500 | D18: =COUNTIF(SalesData[Service],A18) -> 202 | E18: =IFERROR(AVERAGEIF(SalesData[Service],A18,SalesData[Profit_Margin_Pct]),0) -> 32.251584 | F18: =IFERROR(B18/SUM(SalesData[Revenue]),0) -> 0.13290725
A19: Content Marketing | B19: =SUMIF(SalesData[Service],A19,SalesData[Revenue]) -> 8179100 | C19: =SUMIF(SalesData[Service],A19,SalesData[Profit]) -> 2639800 | D19: =COUNTIF(SalesData[Service],A19) -> 186 | E19: =IFERROR(AVERAGEIF(SalesData[Service],A19,SalesData[Profit_Margin_Pct]),0) -> 31.601129 | F19: =IFERROR(B19/SUM(SalesData[Revenue]),0) -> 0.11704946
A20: PPC | B20: =SUMIF(SalesData[Service],A20,SalesData[Revenue]) -> 8826000 | C20: =SUMIF(SalesData[Service],A20,SalesData[Profit]) -> 2830200 | D20: =COUNTIF(SalesData[Service],A20) -> 188 | E20: =IFERROR(AVERAGEIF(SalesData[Service],A20,SalesData[Profit_Margin_Pct]),0) -> 31.170053 | F20: =IFERROR(B20/SUM(SalesData[Revenue]),0) -> 0.12630711
A21: Online Reputation Management | B21: =SUMIF(SalesData[Service],A21,SalesData[Revenue]) -> 8592300 | C21: =SUMIF(SalesData[Service],A21,SalesData[Profit]) -> 2910100 | D21: =COUNTIF(SalesData[Service],A21) -> 184 | E21: =IFERROR(AVERAGEIF(SalesData[Service],A21,SalesData[Profit_Margin_Pct]),0) -> 33.065109 | F21: =IFERROR(B21/SUM(SalesData[Revenue]),0) -> 0.12296268
A22: Mobile App Development | B22: =SUMIF(SalesData[Service],A22,SalesData[Revenue]) -> 9331700 | C22: =SUMIF(SalesData[Service],A22,SalesData[Profit]) -> 2932000 | D22: =COUNTIF(SalesData[Service],A22) -> 209 | E22: =IFERROR(AVERAGEIF(SalesData[Service],A22,SalesData[Profit_Margin_Pct]),0) -> 30.218134 | F22: =IFERROR(B22/SUM(SalesData[Revenue]),0) -> 0.13354408
A26: CUSTOMER RANKING
A27: Rank | B27: Client ID | C27: Projects | D27: Revenue | E27: Profit | F27: Avg Rating
A28: 1 | B28: C0050 | C28: =COUNTIF(SalesData[Client_ID],B28) -> 9 | D28: =SUMIF(SalesData[Client_ID],B28,SalesData[Revenue]) -> 528400 | E28: =SUMIF(SalesData[Client_ID],B28,SalesData[Profit]) -> 166900 | F28: =IFERROR(AVERAGEIF(SalesData[Client_ID],B28,SalesData[Customer_Rating]),0) -> 4.5888889
A29: 2 | B29: C0344 | C29: =COUNTIF(SalesData[Client_ID],B29) -> 9 | D29: =SUMIF(SalesData[Client_ID],B29,SalesData[Revenue]) -> 509600 | E29: =SUMIF(SalesData[Client_ID],B29,SalesData[Profit]) -> 178900 | F29: =IFERROR(AVERAGEIF(SalesData[Client_ID],B29,SalesData[Customer_Rating]),0) -> 3.9333333
A30: 3 | B30: C0086 | C30: =COUNTIF(SalesData[Client_ID],B30) -> 9 | D30: =SUMIF(SalesData[Client_ID],B30,SalesData[Revenue]) -> 445000 | E30: =SUMIF(SalesData[Client_ID],B30,SalesData[Profit]) -> 120100 | F30: =IFERROR(AVERAGEIF(SalesData[Client_ID],B30,SalesData[Customer_Rating]),0) -> 3.7555556
A31: 4 | B31: C0241 | C31: =COUNTIF(SalesData[Client_ID],B31) -> 8 | D31: =SUMIF(SalesData[Client_ID],B31,SalesData[Revenue]) -> 440400 | E31: =SUMIF(SalesData[Client_ID],B31,SalesData[Profit]) -> 107700 | F31: =IFERROR(AVERAGEIF(SalesData[Client_ID],B31,SalesData[Customer_Rating]),0) -> 3.975
A32: 5 | B32: C0047 | C32: =COUNTIF(SalesData[Client_ID],B32) -> 8 | D32: =SUMIF(SalesData[Client_ID],B32,SalesData[Revenue]) -> 432300 | E32: =SUMIF(SalesData[Client_ID],B32,SalesData[Profit]) -> 118800 | F32: =IFERROR(AVERAGEIF(SalesData[Client_ID],B32,SalesData[Customer_Rating]),0) -> 3.9125
A33: 6 | B33: C0089 | C33: =COUNTIF(SalesData[Client_ID],B33) -> 5 | D33: =SUMIF(SalesData[Client_ID],B33,SalesData[Revenue]) -> 407000 | E33: =SUMIF(SalesData[Client_ID],B33,SalesData[Profit]) -> 176800 | F33: =IFERROR(AVERAGEIF(SalesData[Client_ID],B33,SalesData[Customer_Rating]),0) -> 4.4
A34: 7 | B34: C0203 | C34: =COUNTIF(SalesData[Client_ID],B34) -> 7 | D34: =SUMIF(SalesData[Client_ID],B34,SalesData[Revenue]) -> 383000 | E34: =SUMIF(SalesData[Client_ID],B34,SalesData[Profit]) -> 120000 | F34: =IFERROR(AVERAGEIF(SalesData[Client_ID],B34,SalesData[Customer_Rating]),0) -> 4.2571429
A35: 8 | B35: C0204 | C35: =COUNTIF(SalesData[Client_ID],B35) -> 8 | D35: =SUMIF(SalesData[Client_ID],B35,SalesData[Revenue]) -> 378200 | E35: =SUMIF(SalesData[Client_ID],B35,SalesData[Profit]) -> 106300 | F35: =IFERROR(AVERAGEIF(SalesData[Client_ID],B35,SalesData[Customer_Rating]),0) -> 4.1375
A36: 9 | B36: C0322 | C36: =COUNTIF(SalesData[Client_ID],B36) -> 7 | D36: =SUMIF(SalesData[Client_ID],B36,SalesData[Revenue]) -> 376900 | E36: =SUMIF(SalesData[Client_ID],B36,SalesData[Profit]) -> 122100 | F36: =IFERROR(AVERAGEIF(SalesData[Client_ID],B36,SalesData[Customer_Rating]),0) -> 3.7571429
A37: 10 | B37: C0218 | C37: =COUNTIF(SalesData[Client_ID],B37) -> 6 | D37: =SUMIF(SalesData[Client_ID],B37,SalesData[Revenue]) -> 374200 | E37: =SUMIF(SalesData[Client_ID],B37,SalesData[Profit]) -> 123800 | F37: =IFERROR(AVERAGEIF(SalesData[Client_ID],B37,SalesData[Customer_Rating]),0) -> 3.8666667
A38: 11 | B38: C0348 | C38: =COUNTIF(SalesData[Client_ID],B38) -> 7 | D38: =SUMIF(SalesData[Client_ID],B38,SalesData[Revenue]) -> 372700 | E38: =SUMIF(SalesData[Client_ID],B38,SalesData[Profit]) -> 93700 | F38: =IFERROR(AVERAGEIF(SalesData[Client_ID],B38,SalesData[Customer_Rating]),0) -> 4.3
A39: 12 | B39: C0403 | C39: =COUNTIF(SalesData[Client_ID],B39) -> 6 | D39: =SUMIF(SalesData[Client_ID],B39,SalesData[Revenue]) -> 365700 | E39: =SUMIF(SalesData[Client_ID],B39,SalesData[Profit]) -> 102000 | F39: =IFERROR(AVERAGEIF(SalesData[Client_ID],B39,SalesData[Customer_Rating]),0) -> 4.2833333
... A42: 15 | B42: C0233 | C42: =COUNTIF(SalesData[Client_ID],B42) -> 7 | D42: =SUMIF(SalesData[Client_ID],B42,SalesData[Revenue]) -> 362700 | E42: =SUMIF(SalesData[Client_ID],B42,SalesData[Profit]) -> 116400 | F42: =IFERROR(AVERAGEIF(SalesData[Client_ID],B42,SalesData[Customer_Rating]),0) -> 3.8
A45: MARKETING / LEAD SOURCE PERFORMANCE
A46: Lead Source | B46: Revenue | C46: Profit | D46: Projects | E46: Marketing Spend | F46: ROI
A47: Direct | B47: =SUMIF(SalesData[Lead_Source],A47,SalesData[Revenue]) -> 13274500 | C47: =SUMIF(SalesData[Lead_Source],A47,SalesData[Profit]) -> 4361600 | D47: =COUNTIF(SalesData[Lead_Source],A47) -> 268 | E47: =SUMIF(SalesData[Lead_Source],A47,SalesData[Marketing_Spend]) -> 1428400 | F47: =IFERROR((B47-E47)/E47,0) -> 8.2932652
A48: Email Campaign | B48: =SUMIF(SalesData[Lead_Source],A48,SalesData[Revenue]) -> 10926800 | C48: =SUMIF(SalesData[Lead_Source],A48,SalesData[Profit]) -> 3566100 | D48: =COUNTIF(SalesData[Lead_Source],A48) -> 246 | E48: =SUMIF(SalesData[Lead_Source],A48,SalesData[Marketing_Spend]) -> 1151100 | F48: =IFERROR((B48-E48)/E48,0) -> 8.4924854
A49: Google | B49: =SUMIF(SalesData[Lead_Source],A49,SalesData[Revenue]) -> 11135800 | C49: =SUMIF(SalesData[Lead_Source],A49,SalesData[Profit]) -> 3613100 | D49: =COUNTIF(SalesData[Lead_Source],A49) -> 232 | E49: =SUMIF(SalesData[Lead_Source],A49,SalesData[Marketing_Spend]) -> 1206300 | F49: =IFERROR((B49-E49)/E49,0) -> 8.2313686
A50: Partner | B50: =SUMIF(SalesData[Lead_Source],A50,SalesData[Revenue]) -> 11973600 | C50: =SUMIF(SalesData[Lead_Source],A50,SalesData[Profit]) -> 3837800 | D50: =COUNTIF(SalesData[Lead_Source],A50) -> 262 | E50: =SUMIF(SalesData[Lead_Source],A50,SalesData[Marketing_Spend]) -> 1352800 | F50: =IFERROR((B50-E50)/E50,0) -> 7.8509758
A51: Referral | B51: =SUMIF(SalesData[Lead_Source],A51,SalesData[Revenue]) -> 10488100 | C51: =SUMIF(SalesData[Lead_Source],A51,SalesData[Profit]) -> 3312400 | D51: =COUNTIF(SalesData[Lead_Source],A51) -> 233 | E51: =SUMIF(SalesData[Lead_Source],A51,SalesData[Marketing_Spend]) -> 1170800 | F51: =IFERROR((B51-E51)/E51,0) -> 7.9580629
A52: Social Media | B52: =SUMIF(SalesData[Lead_Source],A52,SalesData[Revenue]) -> 11726200 | C52: =SUMIF(SalesData[Lead_Source],A52,SalesData[Profit]) -> 3951200 | D52: =COUNTIF(SalesData[Lead_Source],A52) -> 248 | E52: =SUMIF(SalesData[Lead_Source],A52,SalesData[Marketing_Spend]) -> 1319900 | F52: =IFERROR((B52-E52)/E52,0) -> 7.8841579
A53: Unknown | B53: =SUMIF(SalesData[Lead_Source],A53,SalesData[Revenue]) -> 352300 | C53: =SUMIF(SalesData[Lead_Source],A53,SalesData[Profit]) -> 92100 | D53: =COUNTIF(SalesData[Lead_Source],A53) -> 12 | E53: =SUMIF(SalesData[Lead_Source],A53,SalesData[Marketing_Spend]) -> 31000 | F53: =IFERROR((B53-E53)/E53,0) -> 10.364516
A60: INTERMEDIATE VISUAL SUMMARY
A61: Service | B61: Revenue | C61: Profit | D61: Margin
A62: Mobile App Development | B62: =SUMIF(SalesData[Service],A62,SalesData[Revenue]) -> 9331700 | C62: =SUMIF(SalesData[Service],A62,SalesData[Profit]) -> 2932000 | D62: =IFERROR(AVERAGEIF(SalesData[Service],A62,SalesData[Profit_Margin_Pct]),0) -> 30.218134
A63: Web Development | B63: =SUMIF(SalesData[Service],A63,SalesData[Revenue]) -> 9287200 | C63: =SUMIF(SalesData[Service],A63,SalesData[Profit]) -> 3033500 | D63: =IFERROR(AVERAGEIF(SalesData[Service],A63,SalesData[Profit_Margin_Pct]),0) -> 32.251584
A64: PPC | B64: =SUMIF(SalesData[Service],A64,SalesData[Revenue]) -> 8826000 | C64: =SUMIF(SalesData[Service],A64,SalesData[Profit]) -> 2830200 | D64: =IFERROR(AVERAGEIF(SalesData[Service],A64,SalesData[Profit_Margin_Pct]),0) -> 31.170053
A65: Social Media Marketing | B65: =SUMIF(SalesData[Service],A65,SalesData[Revenue]) -> 8645500 | C65: =SUMIF(SalesData[Service],A65,SalesData[Profit]) -> 2735400 | D65: =IFERROR(AVERAGEIF(SalesData[Service],A65,SalesData[Profit_Margin_Pct]),0) -> 31.681755
A66: Online Reputation Management | B66: =SUMIF(SalesData[Service],A66,SalesData[Revenue]) -> 8592300 | C66: =SUMIF(SalesData[Service],A66,SalesData[Profit]) -> 2910100 | D66: =IFERROR(AVERAGEIF(SalesData[Service],A66,SalesData[Profit_Margin_Pct]),0) -> 33.065109
A67: Web Design | B67: =SUMIF(SalesData[Service],A67,SalesData[Revenue]) -> 8576500 | C67: =SUMIF(SalesData[Service],A67,SalesData[Profit]) -> 2898700 | D67: =IFERROR(AVERAGEIF(SalesData[Service],A67,SalesData[Profit_Margin_Pct]),0) -> 32.972759
A68: SEO | B68: =SUMIF(SalesData[Service],A68,SalesData[Revenue]) -> 8439000 | C68: =SUMIF(SalesData[Service],A68,SalesData[Profit]) -> 2754600 | D68: =IFERROR(AVERAGEIF(SalesData[Service],A68,SalesData[Profit_Margin_Pct]),0) -> 32.063
A69: Content Marketing | B69: =SUMIF(SalesData[Service],A69,SalesData[Revenue]) -> 8179100 | C69: =SUMIF(SalesData[Service],A69,SalesData[Profit]) -> 2639800 | D69: =IFERROR(AVERAGEIF(SalesData[Service],A69,SalesData[Profit_Margin_Pct]),0) -> 31.601129

Sheet Intermediate_Insights
A4: EVIDENCE-BACKED INTERMEDIATE FINDINGS
A6: 2. Mobile App Development leads revenue at ₹9,331,700, while Web Development leads total profit at ₹3,033,500.
A7: 3. 358 of 405 clients have multiple projects (88.4%), providing a measurable repeat-business segment.
A8: 4. Direct is the largest lead source by revenue; its marketing spend should be considered alongside revenue when evaluating performance.
A9: 5. Bengaluru is the highest-revenue region; regional performance should be compared using both revenue and margin.
A10: 6. Education is the largest industry by revenue and is a useful segment for deeper customer and service analysis.
A13: DECISION-ORIENTED RECOMMENDATIONS
A15: 2. Compare service volume with profit margin before prioritizing growth.
A16: 3. Use repeat-client behavior to identify services that can support retention and follow-up opportunities.
A17: 4. Evaluate lead sources using both revenue and marketing spend rather than project count alone.
A18: 5. Investigate high-revenue regions or industries where margins are comparatively weaker.
A19: 6. Use the advanced Power BI dashboard to filter these findings by time, service, region, industry and client type.
